memory.sv
module memory #(parameter ADDR_WIDTH = 8, DATA_WIDTH = 32) (
    input wire clk,
    input wire rst_n,
    input wire [ADDR_WIDTH-1:0] addr,
    input wire [DATA_WIDTH-1:0] data_in,
    input wire write_enable,
    output reg [DATA_WIDTH-1:0] data_out
);
    localparam int WORDS = 1 << (ADDR_WIDTH - 2); // address should be a multiple of 4 (f e d c b a 0 0)

    reg [DATA_WIDTH-1:0] mem [0:WORDS-1]; // array

    always @(posedge clk) begin
      if (!rst_n) begin
          // reset mem
          for (int i = 0; i < WORDS; i = i + 1) begin
              mem[i] <= '0;
          end
      end
      else if (write_enable && addr[1:0] == 2'b00) begin
          mem[addr[ADDR_WIDTH-1:2]] <= data_in;
      end
    end

    assign data_out = mem[addr[ADDR_WIDTH-1:2]]; // read data from memory

endmodule

tests/test_memory.sv
`timescale 1ns/1ps

module test_memory;

  localparam int WORDS = 1024; // 64 words of memory
  localparam int DATA_WIDTH = 32;
  localparam real CLK_PERIOD = 10.0; // 100 MHz clock
  localparam real CLK_HALF_PERIOD = CLK_PERIOD / 2.0;
  reg test_failed;

  task finish;
    begin
      if (test_failed) begin
        $display("Test failed!");
      end else begin
        $display("Test passed!");
      end
      $finish; // End simulation
    end
  endtask

  // dut io
  reg clk;
  reg rst_n;
  reg [DATA_WIDTH-1:0] addr;
  reg [DATA_WIDTH-1:0] data_in;
  reg write_enable;
  wire [DATA_WIDTH-1:0] data_out;

  // dut instantiation
  memory #(
    .WORDS(WORDS),
    .DATA_WIDTH(DATA_WIDTH)
  ) dut (
    .clk(clk),
    .rst_n(rst_n),
    .addr(addr),
    .data_in(data_in),
    .write_enable(write_enable),
    .data_out(data_out)
  );

  // clock
  initial begin
    clk = 0;
    forever begin
      #(CLK_HALF_PERIOD) clk = !clk;
    end
  end

  task write_word(input [DATA_WIDTH-1:0] wad, input [DATA_WIDTH-1:0] wdt);
    begin
      @(negedge clk);
      addr = wad;
      data_in = wdt;
      write_enable = 1;
      @(negedge clk); // wait for write to complete
      write_enable = 0;
      data_in = '0;
    end
  endtask

  task read_word(input [DATA_WIDTH-1:0] rad, input [DATA_WIDTH-1:0] rexp);
    begin
      @(negedge clk);
      addr = rad;
      #1; // wait for data_out to be updated
      if (data_out !== rexp) begin
        test_failed = 1;
        $display("[%0t] error: addr=0x%0h expected=0x%08x, got=0x%08x", $time, addr, rexp, data_out);
      end else begin
        $display("[%0t] OK: addr=0x%0h data=0x%08x", $time, addr, data_out);
      end
    end
  endtask

  initial begin
    $dumpfile("./tests/results/test_memory.vcd");
    $dumpvars(0, test_memory);

    addr = '0;
    data_in = '0;
    write_enable = 0;

    rst_n = 0; // pull reset low
    repeat (2) @(posedge clk); // @ second posedge clk
    rst_n = 1; // release reset
    @(posedge clk);

    // read uninitialized memory
    read_word(32'h00000010, 32'h0);
    read_word(32'h00000000, 32'h0);
    read_word(32'h00000008, 32'h0);

    repeat (2) @(posedge clk); // rest for two clock cycles (20ns)

    repeat (100) begin
      reg [DATA_WIDTH-1:0] rs;
      reg [DATA_WIDTH-1:0] rd;

      rs = {$random} & ~(8-1) & 32'h000000FF; // random & bit_not(7) = random & !...111 = random000 = byte-aligned address; then set the first 24 bits to zero to keep within the 256 bytes of memory
      rd = {$random};
      write_word(rs, rd); // write random data to random address
      read_word(rs, rd); // read back the value
    end

    repeat (2) @(posedge clk); // wait for clock edges to capture the last event.
    finish;
  end

endmodule

tests/results/test_memory.vcd
$date
	Sun Aug 17 08:46:39 2025
$end
$version
	Icarus Verilog
$end
$timescale
	1ps
$end
$scope module test_memory $end
$var wire 32 ! data_out [31:0] $end
$var reg 32 " addr [31:0] $end
$var reg 1 # clk $end
$var reg 32 $ data_in [31:0] $end
$var reg 1 % rst_n $end
$var reg 1 & test_failed $end
$var reg 1 ' write_enable $end
$scope module dut $end
$var wire 32 ( addr [31:0] $end
$var wire 1 # clk $end
$var wire 32 ) data_in [31:0] $end
$var wire 32 * data_out [31:0] $end
$var wire 1 % rst_n $end
$var wire 1 ' write_enable $end
$scope begin $ivl_for_loop0 $end
$var integer 32 + i [31:0] $end
$upscope $end
$upscope $end
$scope begin $unm_blk_15 $end
$var reg 32 , rd [31:0] $end
$var reg 32 - rs [31:0] $end
$upscope $end
$scope task finish $end
$upscope $end
$scope task read_word $end
$var reg 32 . rad [31:0] $end
$var reg 32 / rexp [31:0] $end
$upscope $end
$scope task write_word $end
$var reg 32 0 wad [31:0] $end
$var reg 32 1 wdt [31:0] $end
$upscope $end
$upscope $end
$enddefinitions $end
#0
$dumpvars
bx 1
bx 0
bx /
bx .
bx -
bx ,
b0 +
bx *
b0 )
b0 (
0'
x&
0%
b0 $
0#
b0 "
bx !
$end
#5000
b0 !
b0 *
b10000000000 +
1#
#10000
0#
#15000
b10000000000 +
1%
1#
#20000
0#
#25000
b0 /
b10000 .
1#
#30000
b10000 "
b10000 (
0#
#31000
b0 .
#35000
1#
#40000
b0 "
b0 (
0#
#41000
b1000 .
#45000
1#
#50000
b1000 "
b1000 (
0#
#55000
1#
#60000
0#
#65000
b11000000100010010101111010000001 1
b100000 0
b11000000100010010101111010000001 ,
b100000 -
1#
#70000
1'
b11000000100010010101111010000001 $
b11000000100010010101111010000001 )
b100000 "
b100000 (
0#
#75000
b11000000100010010101111010000001 !
b11000000100010010101111010000001 *
1#
#80000
b11000000100010010101111010000001 /
b100000 .
b0 $
b0 )
0'
0#
#85000
1#
#90000
0#
#91000
b10110001111100000101011001100011 1
b1000 0
b10110001111100000101011001100011 ,
b1000 -
#95000
1#
#100000
1'
b10110001111100000101011001100011 $
b10110001111100000101011001100011 )
b0 !
b0 *
b1000 "
b1000 (
0#
#105000
b10110001111100000101011001100011 !
b10110001111100000101011001100011 *
1#
#110000
b10110001111100000101011001100011 /
b1000 .
b0 $
b0 )
0'
0#
#115000
1#
#120000
0#
#121000
b1000110110111111001100110001101 1
b1000110110111111001100110001101 ,
#125000
1#
#130000
1'
b1000110110111111001100110001101 $
b1000110110111111001100110001101 )
0#
#135000
b1000110110111111001100110001101 !
b1000110110111111001100110001101 *
1#
#140000
b1000110110111111001100110001101 /
b0 $
b0 )
0'
0#
#145000
1#
#150000
0#
#151000
b10001001001101110101001000010010 1
b1100000 0
b10001001001101110101001000010010 ,
b1100000 -
#155000
1#
#160000
1'
b10001001001101110101001000010010 $
b10001001001101110101001000010010 )
b0 !
b0 *
b1100000 "
b1100000 (
0#
#165000
b10001001001101110101001000010010 !
b10001001001101110101001000010010 *
1#
#170000
b10001001001101110101001000010010 /
b1100000 .
b0 $
b0 )
0'
0#
#175000
1#
#180000
0#
#181000
b110110101111100110100001101 1
b0 0
b110110101111100110100001101 ,
b0 -
#185000
1#
#190000
1'
b110110101111100110100001101 $
b110110101111100110100001101 )
b0 !
b0 *
b0 "
b0 (
0#
#195000
b110110101111100110100001101 !
b110110101111100110100001101 *
1#
#200000
b110110101111100110100001101 /
b0 .
b0 $
b0 )
0'
0#
#205000
1#
#210000
0#
#211000
b11110100011011100110100111101 1
b1110000 0
b11110100011011100110100111101 ,
b1110000 -
#215000
1#
#220000
1'
b11110100011011100110100111101 $
b11110100011011100110100111101 )
b0 !
b0 *
b1110000 "
b1110000 (
0#
#225000
b11110100011011100110100111101 !
b11110100011011100110100111101 *
1#
#230000
b11110100011011100110100111101 /
b1110000 .
b0 $
b0 )
0'
0#
#235000
1#
#240000
0#
#241000
b1000110001011011111011110001100 1
b11101000 0
b1000110001011011111011110001100 ,
b11101000 -
#245000
1#
#250000
1'
b1000110001011011111011110001100 $
b1000110001011011111011110001100 )
b0 !
b0 *
b11101000 "
b11101000 (
0#
#255000
b1000110001011011111011110001100 !
b1000110001011011111011110001100 *
1#
#260000
b1000110001011011111011110001100 /
b11101000 .
b0 $
b0 )
0'
0#
#265000
1#
#270000
0#
#271000
b11100011001101110010010011000110 1
b11111000 0
b11100011001101110010010011000110 ,
b11111000 -
#275000
1#
#280000
1'
b11100011001101110010010011000110 $
b11100011001101110010010011000110 )
b0 !
b0 *
b11111000 "
b11111000 (
0#
#285000
b11100011001101110010010011000110 !
b11100011001101110010010011000110 *
1#
#290000
b11100011001101110010010011000110 /
b11111000 .
b0 $
b0 )
0'
0#
#295000
1#
#300000
0#
#301000
b11010101000100111101001010101010 1
b11000000 0
b11010101000100111101001010101010 ,
b11000000 -
#305000
1#
#310000
1'
b11010101000100111101001010101010 $
b11010101000100111101001010101010 )
b0 !
b0 *
b11000000 "
b11000000 (
0#
#315000
b11010101000100111101001010101010 !
b11010101000100111101001010101010 *
1#
#320000
b11010101000100111101001010101010 /
b11000000 .
b0 $
b0 )
0'
0#
#325000
1#
#330000
0#
#331000
b10111011110100100111001001110111 1
b11100000 0
b10111011110100100111001001110111 ,
b11100000 -
#335000
1#
#340000
1'
b10111011110100100111001001110111 $
b10111011110100100111001001110111 )
b0 !
b0 *
b11100000 "
b11100000 (
0#
#345000
b10111011110100100111001001110111 !
b10111011110100100111001001110111 *
1#
#350000
b10111011110100100111001001110111 /
b11100000 .
b0 $
b0 )
0'
0#
#355000
1#
#360000
0#
#361000
b1000111111011001101101110001111 1
b10000 0
b1000111111011001101101110001111 ,
b10000 -
#365000
1#
#370000
1'
b1000111111011001101101110001111 $
b1000111111011001101101110001111 )
b0 !
b0 *
b10000 "
b10000 (
0#
#375000
b1000111111011001101101110001111 !
b1000111111011001101101110001111 *
1#
#380000
b1000111111011001101101110001111 /
b10000 .
b0 $
b0 )
0'
0#
#385000
1#
#390000
0#
#391000
b11100111011101101001011011001110 1
b11110000 0
b11100111011101101001011011001110 ,
b11110000 -
#395000
1#
#400000
1'
b11100111011101101001011011001110 $
b11100111011101101001011011001110 )
b0 !
b0 *
b11110000 "
b11110000 (
0#
#405000
b11100111011101101001011011001110 !
b11100111011101101001011011001110 *
1#
#410000
b11100111011101101001011011001110 /
b11110000 .
b0 $
b0 )
0'
0#
#415000
1#
#420000
0#
#421000
b11100010110010100100111011000101 1
b11101000 0
b11100010110010100100111011000101 ,
b11101000 -
#425000
1#
#430000
1'
b11100010110010100100111011000101 $
b11100010110010100100111011000101 )
b1000110001011011111011110001100 !
b1000110001011011111011110001100 *
b11101000 "
b11101000 (
0#
#435000
b11100010110010100100111011000101 !
b11100010110010100100111011000101 *
1#
#440000
b11100010110010100100111011000101 /
b11101000 .
b0 $
b0 )
0'
0#
#445000
1#
#450000
0#
#451000
b11011110100011100010100010111101 1
b1011000 0
b11011110100011100010100010111101 ,
b1011000 -
#455000
1#
#460000
1'
b11011110100011100010100010111101 $
b11011110100011100010100010111101 )
b0 !
b0 *
b1011000 "
b1011000 (
0#
#465000
b11011110100011100010100010111101 !
b11011110100011100010100010111101 *
1#
#470000
b11011110100011100010100010111101 /
b1011000 .
b0 $
b0 )
0'
0#
#475000
1#
#480000
0#
#481000
b10110010101001110010011001100101 1
b101000 0
b10110010101001110010011001100101 ,
b101000 -
#485000
1#
#490000
1'
b10110010101001110010011001100101 $
b10110010101001110010011001100101 )
b0 !
b0 *
b101000 "
b101000 (
0#
#495000
b10110010101001110010011001100101 !
b10110010101001110010011001100101 *
1#
#500000
b10110010101001110010011001100101 /
b101000 .
b0 $
b0 )
0'
0#
#505000
1#
#510000
0#
#511000
b101011100111000011100001010 1
b1100000 0
b101011100111000011100001010 ,
b1100000 -
#515000
1#
#520000
1'
b101011100111000011100001010 $
b101011100111000011100001010 )
b10001001001101110101001000010010 !
b10001001001101110101001000010010 *
b1100000 "
b1100000 (
0#
#525000
b101011100111000011100001010 !
b101011100111000011100001010 *
1#
#530000
b101011100111000011100001010 /
b1100000 .
b0 $
b0 )
0'
0#
#535000
1#
#540000
0#
#541000
b10000011001000010000100100000 1
b10000000 0
b10000011001000010000100100000 ,
b10000000 -
#545000
1#
#550000
1'
b10000011001000010000100100000 $
b10000011001000010000100100000 )
b0 !
b0 *
b10000000 "
b10000000 (
0#
#555000
b10000011001000010000100100000 !
b10000011001000010000100100000 *
1#
#560000
b10000011001000010000100100000 /
b10000000 .
b0 $
b0 )
0'
0#
#565000
1#
#570000
0#
#571000
b11001110110011001100110010011101 1
b10101000 0
b11001110110011001100110010011101 ,
b10101000 -
#575000
1#
#580000
1'
b11001110110011001100110010011101 $
b11001110110011001100110010011101 )
b0 !
b0 *
b10101000 "
b10101000 (
0#
#585000
b11001110110011001100110010011101 !
b11001110110011001100110010011101 *
1#
#590000
b11001110110011001100110010011101 /
b10101000 .
b0 $
b0 )
0'
0#
#595000
1#
#600000
0#
#601000
b10001001100000111011100000010011 1
b10010000 0
b10001001100000111011100000010011 ,
b10010000 -
#605000
1#
#610000
1'
b10001001100000111011100000010011 $
b10001001100000111011100000010011 )
b0 !
b0 *
b10010000 "
b10010000 (
0#
#615000
b10001001100000111011100000010011 !
b10001001100000111011100000010011 *
1#
#620000
b10001001100000111011100000010011 /
b10010000 .
b0 $
b0 )
0'
0#
#625000
1#
#630000
0#
#631000
b10101001101001111101011001010011 1
b1000 0
b10101001101001111101011001010011 ,
b1000 -
#635000
1#
#640000
1'
b10101001101001111101011001010011 $
b10101001101001111101011001010011 )
b1000110110111111001100110001101 !
b1000110110111111001100110001101 *
b1000 "
b1000 (
0#
#645000
b10101001101001111101011001010011 !
b10101001101001111101011001010011 *
1#
#650000
b10101001101001111101011001010011 /
b1000 .
b0 $
b0 )
0'
0#
#655000
1#
#660000
0#
#661000
b11101010101001100010101011010101 1
b1101000 0
b11101010101001100010101011010101 ,
b1101000 -
#665000
1#
#670000
1'
b11101010101001100010101011010101 $
b11101010101001100010101011010101 )
b0 !
b0 *
b1101000 "
b1101000 (
0#
#675000
b11101010101001100010101011010101 !
b11101010101001100010101011010101 *
1#
#680000
b11101010101001100010101011010101 /
b1101000 .
b0 $
b0 )
0'
0#
#685000
1#
#690000
0#
#691000
b11010111010101100011111010101110 1
b0 0
b11010111010101100011111010101110 ,
b0 -
#695000
1#
#700000
1'
b11010111010101100011111010101110 $
b11010111010101100011111010101110 )
b110110101111100110100001101 !
b110110101111100110100001101 *
b0 "
b0 (
0#
#705000
b11010111010101100011111010101110 !
b11010111010101100011111010101110 *
1#
#710000
b11010111010101100011111010101110 /
b0 .
b0 $
b0 )
0'
0#
#715000
1#
#720000
0#
#721000
b11100111110001010111001011001111 1
b11000 0
b11100111110001010111001011001111 ,
b11000 -
#725000
1#
#730000
1'
b11100111110001010111001011001111 $
b11100111110001010111001011001111 )
b0 !
b0 *
b11000 "
b11000 (
0#
#735000
b11100111110001010111001011001111 !
b11100111110001010111001011001111 *
1#
#740000
b11100111110001010111001011001111 /
b11000 .
b0 $
b0 )
0'
0#
#745000
1#
#750000
0#
#751000
b101000010010110010100001010 1
b100000 0
b101000010010110010100001010 ,
b100000 -
#755000
1#
#760000
1'
b101000010010110010100001010 $
b101000010010110010100001010 )
b11000000100010010101111010000001 !
b11000000100010010101111010000001 *
b100000 "
b100000 (
0#
#765000
b101000010010110010100001010 !
b101000010010110010100001010 *
1#
#770000
b101000010010110010100001010 /
b100000 .
b0 $
b0 )
0'
0#
#775000
1#
#780000
0#
#781000
b10011110001100010100110000111100 1
b11001000 0
b10011110001100010100110000111100 ,
b11001000 -
#785000
1#
#790000
1'
b10011110001100010100110000111100 $
b10011110001100010100110000111100 )
b0 !
b0 *
b11001000 "
b11001000 (
0#
#795000
b10011110001100010100110000111100 !
b10011110001100010100110000111100 *
1#
#800000
b10011110001100010100110000111100 /
b11001000 .
b0 $
b0 )
0'
0#
#805000
1#
#810000
0#
#811000
b1000101001011100110000110001010 1
b11110000 0
b1000101001011100110000110001010 ,
b11110000 -
#815000
1#
#820000
1'
b1000101001011100110000110001010 $
b1000101001011100110000110001010 )
b11100111011101101001011011001110 !
b11100111011101101001011011001110 *
b11110000 "
b11110000 (
0#
#825000
b1000101001011100110000110001010 !
b1000101001011100110000110001010 *
1#
#830000
b1000101001011100110000110001010 /
b11110000 .
b0 $
b0 )
0'
0#
#835000
1#
#840000
0#
#841000
b11101100010010110011010011011000 1
b1000000 0
b11101100010010110011010011011000 ,
b1000000 -
#845000
1#
#850000
1'
b11101100010010110011010011011000 $
b11101100010010110011010011011000 )
b0 !
b0 *
b1000000 "
b1000000 (
0#
#855000
b11101100010010110011010011011000 !
b11101100010010110011010011011000 *
1#
#860000
b11101100010010110011010011011000 /
b1000000 .
b0 $
b0 )
0'
0#
#865000
1#
#870000
0#
#871000
b11000100100010100001001010001001 1
b1111000 0
b11000100100010100001001010001001 ,
b1111000 -
#875000
1#
#880000
1'
b11000100100010100001001010001001 $
b11000100100010100001001010001001 )
b0 !
b0 *
b1111000 "
b1111000 (
0#
#885000
b11000100100010100001001010001001 !
b11000100100010100001001010001001 *
1#
#890000
b11000100100010100001001010001001 /
b1111000 .
b0 $
b0 )
0'
0#
#895000
1#
#900000
0#
#901000
b1011011000000100110010110110110 1
b11101000 0
b1011011000000100110010110110110 ,
b11101000 -
#905000
1#
#910000
1'
b1011011000000100110010110110110 $
b1011011000000100110010110110110 )
b11100010110010100100111011000101 !
b11100010110010100100111011000101 *
b11101000 "
b11101000 (
0#
#915000
b1011011000000100110010110110110 !
b1011011000000100110010110110110 *
1#
#920000
b1011011000000100110010110110110 /
b11101000 .
b0 $
b0 )
0'
0#
#925000
1#
#930000
0#
#931000
b1010111000101010001001110101110 1
b11000000 0
b1010111000101010001001110101110 ,
b11000000 -
#935000
1#
#940000
1'
b1010111000101010001001110101110 $
b1010111000101010001001110101110 )
b11010101000100111101001010101010 !
b11010101000100111101001010101010 *
b11000000 "
b11000000 (
0#
#945000
b1010111000101010001001110101110 !
b1010111000101010001001110101110 *
1#
#950000
b1010111000101010001001110101110 /
b11000000 .
b0 $
b0 )
0'
0#
#955000
1#
#960000
0#
#961000
b10101000011111101110100101010 1
b10111000 0
b10101000011111101110100101010 ,
b10111000 -
#965000
1#
#970000
1'
b10101000011111101110100101010 $
b10101000011111101110100101010 )
b0 !
b0 *
b10111000 "
b10111000 (
0#
#975000
b10101000011111101110100101010 !
b10101000011111101110100101010 *
1#
#980000
b10101000011111101110100101010 /
b10111000 .
b0 $
b0 )
0'
0#
#985000
1#
#990000
0#
#991000
b10111000100101111011111001110001 1
b1000 0
b10111000100101111011111001110001 ,
b1000 -
#995000
1#
#1000000
1'
b10111000100101111011111001110001 $
b10111000100101111011111001110001 )
b10101001101001111101011001010011 !
b10101001101001111101011001010011 *
b1000 "
b1000 (
0#
#1005000
b10111000100101111011111001110001 !
b10111000100101111011111001110001 *
1#
#1010000
b10111000100101111011111001110001 /
b1000 .
b0 $
b0 )
0'
0#
#1015000
1#
#1020000
0#
#1021000
b100111111100100101010101001111 1
b10000000 0
b100111111100100101010101001111 ,
b10000000 -
#1025000
1#
#1030000
1'
b100111111100100101010101001111 $
b100111111100100101010101001111 )
b10000011001000010000100100000 !
b10000011001000010000100100000 *
b10000000 "
b10000000 (
0#
#1035000
b100111111100100101010101001111 !
b100111111100100101010101001111 *
1#
#1040000
b100111111100100101010101001111 /
b10000000 .
b0 $
b0 )
0'
0#
#1045000
1#
#1050000
0#
#1051000
b11101000001100011001100111010 1
b111000 0
b11101000001100011001100111010 ,
b111000 -
#1055000
1#
#1060000
1'
b11101000001100011001100111010 $
b11101000001100011001100111010 )
b0 !
b0 *
b111000 "
b111000 (
0#
#1065000
b11101000001100011001100111010 !
b11101000001100011001100111010 *
1#
#1070000
b11101000001100011001100111010 /
b111000 .
b0 $
b0 )
0'
0#
#1075000
1#
#1080000
0#
#1081000
b1010101010100100101100010101 1
b1111000 0
b1010101010100100101100010101 ,
b1111000 -
#1085000
1#
#1090000
1'
b1010101010100100101100010101 $
b1010101010100100101100010101 )
b11000100100010100001001010001001 !
b11000100100010100001001010001001 *
b1111000 "
b1111000 (
0#
#1095000
b1010101010100100101100010101 !
b1010101010100100101100010101 *
1#
#1100000
b1010101010100100101100010101 /
b1111000 .
b0 $
b0 )
0'
0#
#1105000
1#
#1110000
0#
#1111000
b1101100100111000100101111011001 1
b11110000 0
b1101100100111000100101111011001 ,
b11110000 -
#1115000
1#
#1120000
1'
b1101100100111000100101111011001 $
b1101100100111000100101111011001 )
b1000101001011100110000110001010 !
b1000101001011100110000110001010 *
b11110000 "
b11110000 (
0#
#1125000
b1101100100111000100101111011001 !
b1101100100111000100101111011001 *
1#
#1130000
b1101100100111000100101111011001 /
b11110000 .
b0 $
b0 )
0'
0#
#1135000
1#
#1140000
0#
#1141000
b100110001101011111101101001100 1
b1100000 0
b100110001101011111101101001100 ,
b1100000 -
#1145000
1#
#1150000
1'
b100110001101011111101101001100 $
b100110001101011111101101001100 )
b101011100111000011100001010 !
b101011100111000011100001010 *
b1100000 "
b1100000 (
0#
#1155000
b100110001101011111101101001100 !
b100110001101011111101101001100 *
1#
#1160000
b100110001101011111101101001100 /
b1100000 .
b0 $
b0 )
0'
0#
#1165000
1#
#1170000
0#
#1171000
b1000111101110011010000110001111 1
b10011000 0
b1000111101110011010000110001111 ,
b10011000 -
#1175000
1#
#1180000
1'
b1000111101110011010000110001111 $
b1000111101110011010000110001111 )
b0 !
b0 *
b10011000 "
b10011000 (
0#
#1185000
b1000111101110011010000110001111 !
b1000111101110011010000110001111 *
1#
#1190000
b1000111101110011010000110001111 /
b10011000 .
b0 $
b0 )
0'
0#
#1195000
1#
#1200000
0#
#1201000
b11011011110011010110000010110111 1
b11111000 0
b11011011110011010110000010110111 ,
b11111000 -
#1205000
1#
#1210000
1'
b11011011110011010110000010110111 $
b11011011110011010110000010110111 )
b11100011001101110010010011000110 !
b11100011001101110010010011000110 *
b11111000 "
b11111000 (
0#
#1215000
b11011011110011010110000010110111 !
b11011011110011010110000010110111 *
1#
#1220000
b11011011110011010110000010110111 /
b11111000 .
b0 $
b0 )
0'
0#
#1225000
1#
#1230000
0#
#1231000
b10101110011111011001010001011100 1
b10011000 0
b10101110011111011001010001011100 ,
b10011000 -
#1235000
1#
#1240000
1'
b10101110011111011001010001011100 $
b10101110011111011001010001011100 )
b1000111101110011010000110001111 !
b1000111101110011010000110001111 *
b10011000 "
b10011000 (
0#
#1245000
b10101110011111011001010001011100 !
b10101110011111011001010001011100 *
1#
#1250000
b10101110011111011001010001011100 /
b10011000 .
b0 $
b0 )
0'
0#
#1255000
1#
#1260000
0#
#1261000
b1000100110111100011011110001001 1
b1011000 0
b1000100110111100011011110001001 ,
b1011000 -
#1265000
1#
#1270000
1'
b1000100110111100011011110001001 $
b1000100110111100011011110001001 )
b11011110100011100010100010111101 !
b11011110100011100010100010111101 *
b1011000 "
b1011000 (
0#
#1275000
b1000100110111100011011110001001 !
b1000100110111100011011110001001 *
1#
#1280000
b1000100110111100011011110001001 /
b1011000 .
b0 $
b0 )
0'
0#
#1285000
1#
#1290000
0#
#1291000
b11101000001000110011111011010000 1
b1001000 0
b11101000001000110011111011010000 ,
b1001000 -
#1295000
1#
#1300000
1'
b11101000001000110011111011010000 $
b11101000001000110011111011010000 )
b0 !
b0 *
b1001000 "
b1001000 (
0#
#1305000
b11101000001000110011111011010000 !
b11101000001000110011111011010000 *
1#
#1310000
b11101000001000110011111011010000 /
b1001000 .
b0 $
b0 )
0'
0#
#1315000
1#
#1320000
0#
#1321000
b10101000110001111111110001010001 1
b11010000 0
b10101000110001111111110001010001 ,
b11010000 -
#1325000
1#
#1330000
1'
b10101000110001111111110001010001 $
b10101000110001111111110001010001 )
b0 !
b0 *
b11010000 "
b11010000 (
0#
#1335000
b10101000110001111111110001010001 !
b10101000110001111111110001010001 *
1#
#1340000
b10101000110001111111110001010001 /
b11010000 .
b0 $
b0 )
0'
0#
#1345000
1#
#1350000
0#
#1351000
b110000111010111111100001100 1
b10010000 0
b110000111010111111100001100 ,
b10010000 -
#1355000
1#
#1360000
1'
b110000111010111111100001100 $
b110000111010111111100001100 )
b10001001100000111011100000010011 !
b10001001100000111011100000010011 *
b10010000 "
b10010000 (
0#
#1365000
b110000111010111111100001100 !
b110000111010111111100001100 *
1#
#1370000
b110000111010111111100001100 /
b10010000 .
b0 $
b0 )
0'
0#
#1375000
1#
#1380000
0#
#1381000
b1100100010101111110110111001000 1
b11000000 0
b1100100010101111110110111001000 ,
b11000000 -
#1385000
1#
#1390000
1'
b1100100010101111110110111001000 $
b1100100010101111110110111001000 )
b1010111000101010001001110101110 !
b1010111000101010001001110101110 *
b11000000 "
b11000000 (
0#
#1395000
b1100100010101111110110111001000 !
b1100100010101111110110111001000 *
1#
#1400000
b1100100010101111110110111001000 /
b11000000 .
b0 $
b0 )
0'
0#
#1405000
1#
#1410000
0#
#1411000
b11110111100101110110100111101 1
b1110000 0
b11110111100101110110100111101 ,
b1110000 -
#1415000
1#
#1420000
1'
b11110111100101110110100111101 $
b11110111100101110110100111101 )
b11110100011011100110100111101 !
b11110100011011100110100111101 *
b1110000 "
b1110000 (
0#
#1425000
b11110111100101110110100111101 !
b11110111100101110110100111101 *
1#
#1430000
b11110111100101110110100111101 /
b1110000 .
b0 $
b0 )
0'
0#
#1435000
1#
#1440000
0#
#1441000
b10111111000001010000000001111110 1
b10000 0
b10111111000001010000000001111110 ,
b10000 -
#1445000
1#
#1450000
1'
b10111111000001010000000001111110 $
b10111111000001010000000001111110 )
b1000111111011001101101110001111 !
b1000111111011001101101110001111 *
b10000 "
b10000 (
0#
#1455000
b10111111000001010000000001111110 !
b10111111000001010000000001111110 *
1#
#1460000
b10111111000001010000000001111110 /
b10000 .
b0 $
b0 )
0'
0#
#1465000
1#
#1470000
0#
#1471000
b11100110110011110011100111001 1
b1101000 0
b11100110110011110011100111001 ,
b1101000 -
#1475000
1#
#1480000
1'
b11100110110011110011100111001 $
b11100110110011110011100111001 )
b11101010101001100010101011010101 !
b11101010101001100010101011010101 *
b1101000 "
b1101000 (
0#
#1485000
b11100110110011110011100111001 !
b11100110110011110011100111001 *
1#
#1490000
b11100110110011110011100111001 /
b1101000 .
b0 $
b0 )
0'
0#
#1495000
1#
#1500000
0#
#1501000
b11101001111010111111011011010011 1
b11000 0
b11101001111010111111011011010011 ,
b11000 -
#1505000
1#
#1510000
1'
b11101001111010111111011011010011 $
b11101001111010111111011011010011 )
b11100111110001010111001011001111 !
b11100111110001010111001011001111 *
b11000 "
b11000 (
0#
#1515000
b11101001111010111111011011010011 !
b11101001111010111111011011010011 *
1#
#1520000
b11101001111010111111011011010011 /
b11000 .
b0 $
b0 )
0'
0#
#1525000
1#
#1530000
0#
#1531000
b10111100000101001000100001111000 1
b10000000 0
b10111100000101001000100001111000 ,
b10000000 -
#1535000
1#
#1540000
1'
b10111100000101001000100001111000 $
b10111100000101001000100001111000 )
b100111111100100101010101001111 !
b100111111100100101010101001111 *
b10000000 "
b10000000 (
0#
#1545000
b10111100000101001000100001111000 !
b10111100000101001000100001111000 *
1#
#1550000
b10111100000101001000100001111000 /
b10000000 .
b0 $
b0 )
0'
0#
#1555000
1#
#1560000
0#
#1561000
b100100100010110100101101001001 1
b1011000 0
b100100100010110100101101001001 ,
b1011000 -
#1565000
1#
#1570000
1'
b100100100010110100101101001001 $
b100100100010110100101101001001 )
b1000100110111100011011110001001 !
b1000100110111100011011110001001 *
b1011000 "
b1011000 (
0#
#1575000
b100100100010110100101101001001 !
b100100100010110100101101001001 *
1#
#1580000
b100100100010110100101101001001 /
b1011000 .
b0 $
b0 )
0'
0#
#1585000
1#
#1590000
0#
#1591000
b10101000011001010111100101010 1
b111000 0
b10101000011001010111100101010 ,
b111000 -
#1595000
1#
#1600000
1'
b10101000011001010111100101010 $
b10101000011001010111100101010 )
b11101000001100011001100111010 !
b11101000001100011001100111010 *
b111000 "
b111000 (
0#
#1605000
b10101000011001010111100101010 !
b10101000011001010111100101010 *
1#
#1610000
b10101000011001010111100101010 /
b111000 .
b0 $
b0 )
0'
0#
#1615000
1#
#1620000
0#
#1621000
b11000011001111110011100010000110 1
b1011000 0
b11000011001111110011100010000110 ,
b1011000 -
#1625000
1#
#1630000
1'
b11000011001111110011100010000110 $
b11000011001111110011100010000110 )
b100100100010110100101101001001 !
b100100100010110100101101001001 *
b1011000 "
b1011000 (
0#
#1635000
b11000011001111110011100010000110 !
b11000011001111110011100010000110 *
1#
#1640000
b11000011001111110011100010000110 /
b1011000 .
b0 $
b0 )
0'
0#
#1645000
1#
#1650000
0#
#1651000
b11001110001011111111001010011100 1
b10001000 0
b11001110001011111111001010011100 ,
b10001000 -
#1655000
1#
#1660000
1'
b11001110001011111111001010011100 $
b11001110001011111111001010011100 )
b0 !
b0 *
b10001000 "
b10001000 (
0#
#1665000
b11001110001011111111001010011100 !
b11001110001011111111001010011100 *
1#
#1670000
b11001110001011111111001010011100 /
b10001000 .
b0 $
b0 )
0'
0#
#1675000
1#
#1680000
0#
#1681000
b10010011011111011011110000100110 1
b11111000 0
b10010011011111011011110000100110 ,
b11111000 -
#1685000
1#
#1690000
1'
b10010011011111011011110000100110 $
b10010011011111011011110000100110 )
b11011011110011010110000010110111 !
b11011011110011010110000010110111 *
b11111000 "
b11111000 (
0#
#1695000
b10010011011111011011110000100110 !
b10010011011111011011110000100110 *
1#
#1700000
b10010011011111011011110000100110 /
b11111000 .
b0 $
b0 )
0'
0#
#1705000
1#
#1710000
0#
#1711000
b11010001100010111011010010100011 1
b1110000 0
b11010001100010111011010010100011 ,
b1110000 -
#1715000
1#
#1720000
1'
b11010001100010111011010010100011 $
b11010001100010111011010010100011 )
b11110111100101110110100111101 !
b11110111100101110110100111101 *
b1110000 "
b1110000 (
0#
#1725000
b11010001100010111011010010100011 !
b11010001100010111011010010100011 *
1#
#1730000
b11010001100010111011010010100011 /
b1110000 .
b0 $
b0 )
0'
0#
#1735000
1#
#1740000
0#
#1741000
b11011001110100101001001010110011 1
b101000 0
b11011001110100101001001010110011 ,
b101000 -
#1745000
1#
