memory.sv
module memory #(parameter ADDR_WIDTH = 8, DATA_WIDTH = 32) (
    input wire clk,
    input wire rst_n,
    input wire [ADDR_WIDTH-1:0] addr,
    input wire [DATA_WIDTH-1:0] data_in,
    input wire write_enable,
    output reg [DATA_WIDTH-1:0] data_out
);
    localparam int WORDS = 1 << (ADDR_WIDTH - 2); // address should be a multiple of 4 (f e d c b a 0 0)

    reg [DATA_WIDTH-1:0] mem [0:WORDS-1]; // array

    always @(posedge clk) begin
      if (!rst_n) begin
          // reset mem
          for (int i = 0; i < WORDS; i = i + 1) begin
              mem[i] <= '0;
          end
      end
      else if (write_enable && addr[1:0] == 2'b00) begin
          mem[addr[ADDR_WIDTH-1:2]] <= data_in;
      end
    end

    assign data_out = mem[addr[ADDR_WIDTH-1:2]]; // read data from memory

endmodule

tests/test_memory.sv
`timescale 1ns/1ps

module test_memory;

  localparam int ADDR_WIDTH = 8;
  localparam int DATA_WIDTH = 32;
  localparam real CLK_PERIOD = 10.0; // 100 MHz clock
  localparam real CLK_HALF_PERIOD = CLK_PERIOD / 2.0;

  // dut io
  reg clk;
  reg rst_n;
  reg [ADDR_WIDTH-1:0] addr;
  reg [DATA_WIDTH-1:0] data_in;
  reg write_enable;
  wire [DATA_WIDTH-1:0] data_out;

  initial begin
    $dumpfile("waves.vcd");
    $dumpvars(0, test_memory);
  end

  // dut instantiation
  memory #(
    .ADDR_WIDTH(ADDR_WIDTH),
    .DATA_WIDTH(DATA_WIDTH)
  ) dut (
    .clk(clk),
    .rst_n(rst_n),
    .addr(addr),
    .data_in(data_in),
    .write_enable(write_enable),
    .data_out(data_out)
  );

  // clock
  initial begin
    clk = 0;
    forever begin
      #(CLK_HALF_PERIOD) clk = !clk;
    end
  end

  task write_word(input [ADDR_WIDTH-1:0] wad, input [DATA_WIDTH-1:0] wdt);
    begin
      @(negedge clk);
      addr = wad;
      data_in = wdt;
      write_enable = 1;
      @(negedge clk); // wait for write to complete
      write_enable = 0;
      data_in = '0;
    end
  endtask

  task read_word(input [ADDR_WIDTH-1:0] rad, input [DATA_WIDTH-1:0] rexp);
    begin
      @(negedge clk);
      addr = rad;
      #1; // wait for data_out to be updated
      if (data_out !== rexp) begin
        $display("[%0t] error: addr=0x%0h expected=0x%08x, got=0x%08x", $time, addr, rexp, data_out);
      end else begin
        $display("[%0t] OK: addr=0x%0h data=0x%08x", $time, addr, data_out);
      end
    end
  endtask

  initial begin
    addr = '0;
    data_in = '0;
    write_enable = 0;

    rst_n = 0; // pull reset low
    repeat (2) @(posedge clk); // @ second posedge clk
    rst_n = 1; // release reset
    @(posedge clk);

    read_word(8'h04, 32'h0); // read uninitialized memory
    read_word(8'h00, 32'h0); // read uninitialized memory
    read_word(8'h08, 32'h0); // read uninitialized memory


    write_word(8'h04, 32'hcafebabe); // write to address 0x04
    read_word(8'h04, 32'hcafebabe); // read back the value

    write_word(8'h00, 32'hdeadbeef); // write to address 0x00
    read_word(8'h00, 32'hdeadbeef); // read back the value


    write_word(8'h08, 32'h12345678); // write to address 0x08
    read_word(8'h08, 32'h12345678); // read back the value

    write_word(8'h02, 32'h11111111); // write to address 0x02 (should not write, misaligned)
    read_word(8'h00, 32'hdeadbeef); // read back the value (should be unchanged)

    write_word(8'h04, 32'h22222222); // write to address 0x04 (should write)
    read_word(8'h04, 32'h22222222); // read back the value

    repeat (10) begin
      reg [ADDR_WIDTH-1:0] rs;
      reg [DATA_WIDTH-1:0] rd;

      rs = {$random} & !(8'h03);
      rd = {$random};
      write_word(rs, rd); // write random data to random address
      read_word(rs, rd); // read back the value
    end

    repeat (2) @(posedge clk); // wait for clock edges to capture the last event.
    $display("all tests passed");
    $finish;
  end

endmodule

tests/results/test_memory.vcd
$date
	Fri Aug 15 13:48:02 2025
$end
$version
	Icarus Verilog
$end
$timescale
	1ps
$end
$scope module test_memory $end
$var wire 32 ! data_out [31:0] $end
$var reg 8 " addr [7:0] $end
$var reg 1 # clk $end
$var reg 32 $ data_in [31:0] $end
$var reg 1 % rst_n $end
$var reg 1 & write_enable $end
$scope module dut $end
$var wire 8 ' addr [7:0] $end
$var wire 1 # clk $end
$var wire 32 ( data_in [31:0] $end
$var wire 32 ) data_out [31:0] $end
$var wire 1 % rst_n $end
$var wire 1 & write_enable $end
$scope begin $ivl_for_loop0 $end
$var integer 32 * i [31:0] $end
$upscope $end
$upscope $end
$scope begin $unm_blk_13 $end
$var reg 32 + rd [31:0] $end
$var reg 8 , rs [7:0] $end
$upscope $end
$scope task read_word $end
$var reg 8 - rad [7:0] $end
$var reg 32 . rexp [31:0] $end
$upscope $end
$scope task write_word $end
$var reg 8 / wad [7:0] $end
$var reg 32 0 wdt [31:0] $end
$upscope $end
$upscope $end
$enddefinitions $end
#0
$dumpvars
bx 0
bx /
bx .
bx -
bx ,
bx +
b0 *
bx )
b0 (
b0 '
0&
0%
b0 $
0#
b0 "
bx !
$end
#5000
b0 !
b0 )
b1000000 *
1#
#10000
0#
#15000
b1000000 *
1%
1#
#20000
0#
#25000
b0 .
b100 -
1#
#30000
b100 "
b100 '
0#
#31000
b0 -
#35000
1#
#40000
b0 "
b0 '
0#
#41000
b1000 -
#45000
1#
#50000
b1000 "
b1000 '
0#
#51000
b11001010111111101011101010111110 0
b100 /
#55000
1#
#60000
1&
b11001010111111101011101010111110 $
b11001010111111101011101010111110 (
b100 "
b100 '
0#
#65000
b11001010111111101011101010111110 !
b11001010111111101011101010111110 )
1#
#70000
b11001010111111101011101010111110 .
b100 -
b0 $
b0 (
0&
0#
#75000
1#
#80000
0#
#81000
b11011110101011011011111011101111 0
b0 /
#85000
1#
#90000
b0 !
b0 )
1&
b11011110101011011011111011101111 $
b11011110101011011011111011101111 (
b0 "
b0 '
0#
#95000
b11011110101011011011111011101111 !
b11011110101011011011111011101111 )
1#
#100000
b11011110101011011011111011101111 .
b0 -
b0 $
b0 (
0&
0#
#105000
1#
#110000
0#
#111000
b10010001101000101011001111000 0
b1000 /
#115000
1#
#120000
b0 !
b0 )
1&
b10010001101000101011001111000 $
b10010001101000101011001111000 (
b1000 "
b1000 '
0#
#125000
b10010001101000101011001111000 !
b10010001101000101011001111000 )
1#
#130000
b10010001101000101011001111000 .
b1000 -
b0 $
b0 (
0&
0#
#135000
1#
#140000
0#
#141000
b10001000100010001000100010001 0
b10 /
#145000
1#
#150000
b11011110101011011011111011101111 !
b11011110101011011011111011101111 )
1&
b10001000100010001000100010001 $
b10001000100010001000100010001 (
b10 "
b10 '
0#
#155000
1#
#160000
b11011110101011011011111011101111 .
b0 -
b0 $
b0 (
0&
0#
#165000
1#
#170000
b0 "
b0 '
0#
#171000
b100010001000100010001000100010 0
b100 /
#175000
1#
#180000
b11001010111111101011101010111110 !
b11001010111111101011101010111110 )
1&
b100010001000100010001000100010 $
b100010001000100010001000100010 (
b100 "
b100 '
0#
#185000
b100010001000100010001000100010 !
b100010001000100010001000100010 )
1#
#190000
b100010001000100010001000100010 .
b100 -
b0 $
b0 (
0&
0#
#195000
1#
#200000
0#
#201000
b11000000100010010101111010000001 0
b0 /
b11000000100010010101111010000001 +
b0 ,
#205000
1#
#210000
b11011110101011011011111011101111 !
b11011110101011011011111011101111 )
1&
b11000000100010010101111010000001 $
b11000000100010010101111010000001 (
b0 "
b0 '
0#
#215000
b11000000100010010101111010000001 !
b11000000100010010101111010000001 )
1#
#220000
b11000000100010010101111010000001 .
b0 -
b0 $
b0 (
0&
0#
#225000
1#
#230000
0#
#231000
b10110001111100000101011001100011 0
b10110001111100000101011001100011 +
#235000
1#
#240000
1&
b10110001111100000101011001100011 $
b10110001111100000101011001100011 (
0#
#245000
b10110001111100000101011001100011 !
b10110001111100000101011001100011 )
1#
#250000
b10110001111100000101011001100011 .
b0 $
b0 (
0&
0#
#255000
1#
#260000
0#
#261000
b1000110110111111001100110001101 0
b1000110110111111001100110001101 +
#265000
1#
#270000
1&
b1000110110111111001100110001101 $
b1000110110111111001100110001101 (
0#
#275000
b1000110110111111001100110001101 !
b1000110110111111001100110001101 )
1#
#280000
b1000110110111111001100110001101 .
b0 $
b0 (
0&
0#
#285000
1#
#290000
0#
#291000
b10001001001101110101001000010010 0
b10001001001101110101001000010010 +
#295000
1#
#300000
1&
b10001001001101110101001000010010 $
b10001001001101110101001000010010 (
0#
#305000
b10001001001101110101001000010010 !
b10001001001101110101001000010010 )
1#
#310000
b10001001001101110101001000010010 .
b0 $
b0 (
0&
0#
#315000
1#
#320000
0#
#321000
b110110101111100110100001101 0
b110110101111100110100001101 +
#325000
1#
#330000
1&
b110110101111100110100001101 $
b110110101111100110100001101 (
0#
#335000
b110110101111100110100001101 !
b110110101111100110100001101 )
1#
#340000
b110110101111100110100001101 .
b0 $
b0 (
0&
0#
#345000
1#
#350000
0#
#351000
b11110100011011100110100111101 0
b11110100011011100110100111101 +
#355000
1#
#360000
1&
b11110100011011100110100111101 $
b11110100011011100110100111101 (
0#
#365000
b11110100011011100110100111101 !
b11110100011011100110100111101 )
1#
#370000
b11110100011011100110100111101 .
b0 $
b0 (
0&
0#
#375000
1#
#380000
0#
#381000
b1000110001011011111011110001100 0
b1000110001011011111011110001100 +
#385000
1#
#390000
1&
b1000110001011011111011110001100 $
b1000110001011011111011110001100 (
0#
#395000
b1000110001011011111011110001100 !
b1000110001011011111011110001100 )
1#
#400000
b1000110001011011111011110001100 .
b0 $
b0 (
0&
0#
#405000
1#
#410000
0#
#411000
b11100011001101110010010011000110 0
b11100011001101110010010011000110 +
#415000
1#
#420000
1&
b11100011001101110010010011000110 $
b11100011001101110010010011000110 (
0#
#425000
b11100011001101110010010011000110 !
b11100011001101110010010011000110 )
1#
#430000
b11100011001101110010010011000110 .
b0 $
b0 (
0&
0#
#435000
1#
#440000
0#
#441000
b11010101000100111101001010101010 0
b11010101000100111101001010101010 +
#445000
1#
#450000
1&
b11010101000100111101001010101010 $
b11010101000100111101001010101010 (
0#
#455000
b11010101000100111101001010101010 !
b11010101000100111101001010101010 )
1#
#460000
b11010101000100111101001010101010 .
b0 $
b0 (
0&
0#
#465000
1#
#470000
0#
#471000
b10111011110100100111001001110111 0
b10111011110100100111001001110111 +
#475000
1#
#480000
1&
b10111011110100100111001001110111 $
b10111011110100100111001001110111 (
0#
#485000
b10111011110100100111001001110111 !
b10111011110100100111001001110111 )
1#
#490000
b10111011110100100111001001110111 .
b0 $
b0 (
0&
0#
