src/signext.sv
import isa_shared::*;

module signext #(parameter DATA_WIDTH = 32) (
    input wire [24:0] instruction,
    input wire [2:0] imm_op,

    output reg [DATA_WIDTH-1:0] sign_extended_data
);
  reg [11:0] extracted_immediate;

  always @* begin
    case (imm_op)
      IMM_3120: extracted_immediate = instruction[24:13]; // extract immediate from 31:20 bits of raw instruction = 24:13 bits of minus opcode instruction
      default: extracted_immediate = '0;
    endcase

    // (32-12 = 20) repeat 11th bit + [11:0]imm => 32 bits
    sign_extended_data = {{(DATA_WIDTH-$bits(extracted_immediate)){extracted_immediate[11]}}, extracted_immediate};
  end


endmodule

tests/test_signext.sv
`timescale 1ns/1ps
import isa_shared::*;

module test_signext;

  localparam int DATA_WIDTH = 32;
  reg [DATA_WIDTH-1:0] expected_immediate;
  reg test_failed;

  task finish;
    begin
      if (test_failed) begin
        $display("Test failed!");
      end else begin
        $display("Test passed!");
      end
      $finish; // End simulation
    end
  endtask

  // dut io
  reg [24:0] instruction;
  reg [2:0] imm_op;
  wire [DATA_WIDTH-1:0] sign_extended_data;

  // dut instantiation
  signext #(
    .DATA_WIDTH(DATA_WIDTH)
  ) dut (
    .instruction(instruction),
    .imm_op(imm_op),
    .sign_extended_data(sign_extended_data)
  );

  // test cases
  initial begin
    $dumpfile("./tests/results/test_signext.vcd");
    $dumpvars(0, test_signext);

    imm_op = isa_shared::IMM_3120;

    repeat (1000) begin
      instruction = {$random};
      expected_immediate = {{(DATA_WIDTH-12){instruction[24]}}, instruction[24:13]};
      #1; // wait for sign_extended_data to be updated
      if (sign_extended_data !== expected_immediate) begin
        test_failed = 0;
        $display("[%0t] error: expected 0b%b, got 0b%b", $time, expected_immediate, sign_extended_data);
      end else begin
        $display("[%0t] OK: 0b%b", $time, sign_extended_data);
      end
    end

    instruction = 25'b000000000000_10101_010_10101; // [24:13] = 0x000 (zero immediate)
    #1;
    if (sign_extended_data !== 32'h00000000) begin
      test_failed = 1;
      $display("[%0t] error: expected 0x%h, got 0x%h", $time, 32'h00000000, sign_extended_data);
    end else begin
      $display("[%0t] OK: 0x%h", $time, sign_extended_data);
    end

    finish; // End simulation
  end

endmodule

tests/results/test_signext.vcd
$date
	Sun Aug 17 10:06:17 2025
$end
$version
	Icarus Verilog
$end
$timescale
	1ps
$end
$scope module test_signext $end
$var wire 32 ! sign_extended_data [31:0] $end
$var reg 32 " expected_immediate [31:0] $end
$var reg 3 # imm_op [2:0] $end
$var reg 25 $ instruction [24:0] $end
$var reg 1 % test_failed $end
$scope module dut $end
$var wire 3 & imm_op [2:0] $end
$var wire 25 ' instruction [24:0] $end
$var reg 12 ( extracted_immediate [11:0] $end
$var reg 32 ) sign_extended_data [31:0] $end
$upscope $end
$scope task finish $end
$upscope $end
$upscope $end
$enddefinitions $end
#0
$dumpvars
b10101001 )
b10101001 (
b101010011010100100100 '
b0 &
x%
b101010011010100100100 $
b0 #
b10101001 "
b10101001 !
$end
#1000
b10001001010 !
b10001001010 )
b10001001010 (
b10001001010 "
b100010010101111010000001 $
b100010010101111010000001 '
#2000
b10000100110 !
b10000100110 )
b10000100110 (
b10000100110 "
b100001001101011000001001 $
b100001001101011000001001 '
#3000
b11111111111111111111111110000010 !
b11111111111111111111111110000010 )
b111110000010 (
b11111111111111111111111110000010 "
b1111100000101011001100011 $
b1111100000101011001100011 '
#4000
b10111001011 !
b10111001011 )
b10111001011 (
b10111001011 "
b101110010111101100001101 $
b101110010111101100001101 '
#5000
b11011111100 !
b11011111100 )
b11011111100 (
b11011111100 "
b110111111001100110001101 $
b110111111001100110001101 '
#6000
b11000010100 !
b11000010100 )
b11000010100 (
b11000010100 "
b110000101000010001100101 $
b110000101000010001100101 '
#7000
b11111111111111111111100110111010 !
b11111111111111111111100110111010 )
b100110111010 (
b11111111111111111111100110111010 "
b1001101110101001000010010 $
b1001101110101001000010010 '
#8000
b11110011111 !
b11110011111 )
b11110011111 (
b11110011111 "
b111100111110001100000001 $
b111100111110001100000001 '
#9000
b11010111110 !
b11010111110 )
b11010111110 (
b11010111110 "
b110101111100110100001101 $
b110101111100110100001101 '
#10000
b11111111111111111111100100011111 !
b11111111111111111111100100011111 )
b100100011111 (
b11111111111111111111100100011111 "
b1001000111111000101110110 $
b1001000111111000101110110 '
#11000
b10001101110 !
b10001101110 )
b10001101110 (
b10001101110 "
b100011011100110100111101 $
b100011011100110100111101 '
#12000
b11010100010 !
b11010100010 )
b11010100010 (
b11010100010 "
b110101000101011111101101 $
b110101000101011111101101 '
#13000
b101101111 !
b101101111 )
b101101111 (
b101101111 "
b1011011111011110001100 $
b1011011111011110001100 '
#14000
b11111101111 !
b11111101111 )
b11111101111 (
b11111101111 "
b111111011110100111111001 $
b111111011110100111111001 '
#15000
b11111111111111111111100110111001 !
b11111111111111111111100110111001 )
b100110111001 (
b11111111111111111111100110111001 "
b1001101110010010011000110 $
b1001101110010010011000110 '
#16000
b11110111100 !
b11110111100 )
b11110111100 (
b11110111100 "
b111101111000010011000101 $
b111101111000010011000101 '
#17000
b11111111111111111111100010011110 !
b11111111111111111111100010011110 )
b100010011110 (
b11111111111111111111100010011110 "
b1000100111101001010101010 $
b1000100111101001010101010 '
#18000
b10101111111 !
b10101111111 )
b10101111111 (
b10101111111 "
b101011111111011111100101 $
b101011111111011111100101 '
#19000
b11111111111111111111111010010011 !
b11111111111111111111111010010011 )
b111010010011 (
b11111111111111111111111010010011 "
b1110100100111001001110111 $
b1110100100111001001110111 '
#20000
b11111111111111111111100110010110 !
b11111111111111111111100110010110 )
b100110010110 (
b11111111111111111111100110010110 "
b1001100101101011000010010 $
b1001100101101011000010010 '
#21000
b11111111111111111111111101100110 !
b11111111111111111111111101100110 )
b111101100110 (
b11111111111111111111111101100110 "
b1111011001101101110001111 $
b1111011001101101110001111 '
#22000
b11111111111111111111100110000011 !
b11111111111111111111100110000011 )
b100110000011 (
b11111111111111111111100110000011 "
b1001100000110100111110010 $
b1001100000110100111110010 '
#23000
b11111111111111111111101110110100 !
b11111111111111111111101110110100 )
b101110110100 (
b11111111111111111111101110110100 "
b1011101101001011011001110 $
b1011101101001011011001110 '
#24000
b11 !
b11 )
b11 (
b11 "
b111101011101000 $
b111101011101000 '
#25000
b11001010010 !
b11001010010 )
b11001010010 (
b11001010010 "
b110010100100111011000101 $
b110010100100111011000101 '
#26000
b1011000010 !
b1011000010 )
b1011000010 (
b1011000010 "
b10110000100100101011100 $
b10110000100100101011100 '
#27000
b10001110001 !
b10001110001 )
b10001110001 (
b10001110001 "
b100011100010100010111101 $
b100011100010100010111101 '
#28000
b10101011010 !
b10101011010 )
b10101011010 (
b10101011010 "
b101010110101100000101101 $
b101010110101100000101101 '
#29000
b10100111001 !
b10100111001 )
b10100111001 (
b10100111001 "
b101001110010011001100101 $
b101001110010011001100101 '
#30000
b11111111111111111111111101111011 !
b11111111111111111111111101111011 )
b111101111011 (
b11111111111111111111111101111011 "
b1111011110110001001100011 $
b1111011110110001001100011 '
#31000
b11111111111111111111101110011100 !
b11111111111111111111101110011100 )
b101110011100 (
b11111111111111111111101110011100 "
b1011100111000011100001010 $
b1011100111000011100001010 '
#32000
b111011001 !
b111011001 )
b111011001 (
b111011001 "
b1110110010001010000000 $
b1110110010001010000000 '
#33000
b1100100001 !
b1100100001 )
b1100100001 (
b1100100001 "
b11001000010000100100000 $
b11001000010000100100000 '
#34000
b11111111111111111111101111000010 !
b11111111111111111111101111000010 )
b101111000010 (
b11111111111111111111101111000010 "
b1011110000100010110101010 $
b1011110000100010110101010 '
#35000
b11001100110 !
b11001100110 )
b11001100110 (
b11001100110 "
b110011001100110010011101 $
b110011001100110010011101 '
#36000
b11111111111111111111100100000001 !
b11111111111111111111100100000001 )
b100100000001 (
b11111111111111111111100100000001 "
b1001000000011111010010110 $
b1001000000011111010010110 '
#37000
b11111111111111111111110000011101 !
b11111111111111111111110000011101 )
b110000011101 (
b11111111111111111111110000011101 "
b1100000111011100000010011 $
b1100000111011100000010011 '
#38000
b10111100001 !
b10111100001 )
b10111100001 (
b10111100001 "
b101111000011100000001101 $
b101111000011100000001101 '
#39000
b11111111111111111111110100111110 !
b11111111111111111111110100111110 )
b110100111110 (
b11111111111111111111110100111110 "
b1101001111101011001010011 $
b1101001111101011001010011 '
#40000
b11111111111111111111110011111110 !
b11111111111111111111110011111110 )
b110011111110 (
b11111111111111111111110011111110 "
b1100111111101110101101011 $
b1100111111101110101101011 '
#41000
b10100110001 !
b10100110001 )
b10100110001 (
b10100110001 "
b101001100010101011010101 $
b101001100010101011010101 '
#42000
b11111111111111111111100010111010 !
b11111111111111111111100010111010 )
b100010111010 (
b11111111111111111111100010111010 "
b1000101110100101000000010 $
b1000101110100101000000010 '
#43000
b11111111111111111111101010110001 !
b11111111111111111111101010110001 )
b101010110001 (
b11111111111111111111101010110001 "
b1010101100011111010101110 $
b1010101100011111010101110 '
#44000
b11111111111 !
b11111111111 )
b11111111111 (
b11111111111 "
b111111111110100100011101 $
b111111111110100100011101 '
#45000
b11111111111111111111111000101011 !
b11111111111111111111111000101011 )
b111000101011 (
b11111111111111111111111000101011 "
b1110001010111001011001111 $
b1110001010111001011001111 '
#46000
b11111111111111111111110000100010 !
b11111111111111111111110000100010 )
b110000100010 (
b11111111111111111111110000100010 "
b1100001000100100100100011 $
b1100001000100100100100011 '
#47000
b11111111111111111111100001001011 !
b11111111111111111111100001001011 )
b100001001011 (
b11111111111111111111100001001011 "
b1000010010110010100001010 $
b1000010010110010100001010 '
#48000
b11111111111111111111101110011000 !
b11111111111111111111101110011000 )
b101110011000 (
b11111111111111111111101110011000 "
b1011100110000101011001010 $
b1011100110000101011001010 '
#49000
b110001010 !
b110001010 )
b110001010 (
b110001010 "
b1100010100110000111100 $
b1100010100110000111100 '
#50000
b11111111111111111111101101000101 !
b11111111111111111111101101000101 )
b101101000101 (
b11111111111111111111101101000101 "
b1011010001011110111110010 $
b1011010001011110111110010 '
#51000
b11111111111111111111100101110011 !
b11111111111111111111100101110011 )
b100101110011 (
b11111111111111111111100101110011 "
b1001011100110000110001010 $
b1001011100110000110001010 '
#52000
b11000100101 !
b11000100101 )
b11000100101 (
b11000100101 "
b110001001011001101000001 $
b110001001011001101000001 '
#53000
b1001011001 !
b1001011001 )
b1001011001 (
b1001011001 "
b10010110011010011011000 $
b10010110011010011011000 '
#54000
b100000111 !
b100000111 )
b100000111 (
b100000111 "
b1000001111001101111000 $
b1000001111001101111000 '
#55000
b10001010000 !
b10001010000 )
b10001010000 (
b10001010000 "
b100010100001001010001001 $
b100010100001001010001001 '
#56000
b11111111111111111111111000101000 !
b11111111111111111111111000101000 )
b111000101000 (
b11111111111111111111111000101000 "
b1110001010000110111101011 $
b1110001010000110111101011 '
#57000
b11111111111111111111100000010011 !
b11111111111111111111100000010011 )
b100000010011 (
b11111111111111111111100000010011 "
b1000000100110010110110110 $
b1000000100110010110110110 '
#58000
b11111111111111111111101001011111 !
b11111111111111111111101001011111 )
b101001011111 (
b11111111111111111111101001011111 "
b1010010111111100111000110 $
b1010010111111100111000110 '
#59000
b11111111111111111111100010101000 !
b11111111111111111111100010101000 )
b100010101000 (
b11111111111111111111100010101000 "
b1000101010001001110101110 $
b1000101010001001110101110 '
#60000
b1110101000 !
b1110101000 )
b1110101000 (
b1110101000 "
b11101010000001010111100 $
b11101010000001010111100 '
#61000
b11111111111111111111100001111110 !
b11111111111111111111100001111110 )
b100001111110 (
b11111111111111111111100001111110 "
b1000011111101110100101010 $
b1000011111101110100101010 '
#62000
b11111111111111111111111010111100 !
b11111111111111111111111010111100 )
b111010111100 (
b11111111111111111111111010111100 "
b1110101111001101000001011 $
b1110101111001101000001011 '
#63000
b10010111101 !
b10010111101 )
b10010111101 (
b10010111101 "
b100101111011111001110001 $
b100101111011111001110001 '
#64000
b11110010010 !
b11110010010 )
b11110010010 (
b11110010010 "
b111100100100000110000101 $
b111100100100000110000101 '
#65000
b11111111111111111111111110010010 !
b11111111111111111111111110010010 )
b111110010010 (
b11111111111111111111111110010010 "
b1111100100101010101001111 $
b1111100100101010101001111 '
#66000
b11111111111111111111111001100011 !
b11111111111111111111111001100011 )
b111001100011 (
b11111111111111111111111001100011 "
b1110011000110000000111011 $
b1110011000110000000111011 '
#67000
b11111111111111111111100000110001 !
b11111111111111111111100000110001 )
b100000110001 (
b11111111111111111111100000110001 "
b1000001100011001100111010 $
b1000001100011001100111010 '
#68000
b11111111111111111111100100011001 !
b11111111111111111111100100011001 )
b100100011001 (
b11111111111111111111100100011001 "
b1001000110011001001111110 $
b1001000110011001001111110 '
#69000
b10101010010 !
b10101010010 )
b10101010010 (
b10101010010 "
b101010100100101100010101 $
b101010100100101100010101 '
#70000
b11011001100 !
b11011001100 )
b11011001100 (
b11011001100 "
b110110011001101111110001 $
b110110011001101111110001 '
#71000
b10011100010 !
b10011100010 )
b10011100010 (
b10011100010 "
b100111000100101111011001 $
b100111000100101111011001 '
#72000
b11111111111111111111100100011000 !
b11111111111111111111100100011000 )
b100100011000 (
b11111111111111111111100100011000 "
b1001000110000011101100010 $
b1001000110000011101100010 '
#73000
b110101111 !
b110101111 )
b110101111 (
b110101111 "
b1101011111101101001100 $
b1101011111101101001100 '
#74000
b11111111111111111111110100001010 !
b11111111111111111111110100001010 )
b110100001010 (
b11111111111111111111110100001010 "
b1101000010101010110011111 $
b1101000010101010110011111 '
#75000
b11111111111111111111110111001101 !
b11111111111111111111110111001101 )
b110111001101 (
b11111111111111111111110111001101 "
b1101110011010000110001111 $
b1101110011010000110001111 '
#76000
b1101101101 !
b1101101101 )
b1101101101 (
b1101101101 "
b11011011010100111111000 $
b11011011010100111111000 '
#77000
b11111111111111111111111001101011 !
b11111111111111111111111001101011 )
b111001101011 (
b11111111111111111111111001101011 "
b1110011010110000010110111 $
b1110011010110000010110111 '
#78000
b11111111111111111111111000100010 !
b11111111111111111111111000100010 )
b111000100010 (
b11111111111111111111111000100010 "
b1110001000101011010011111 $
b1110001000101011010011111 '
#79000
b1111101100 !
b1111101100 )
b1111101100 (
b1111101100 "
b11111011001010001011100 $
b11111011001010001011100 '
#80000
b11111111111111111111111001011110 !
b11111111111111111111111001011110 )
b111001011110 (
b11111111111111111111111001011110 "
b1110010111100000001011011 $
b1110010111100000001011011 '
#81000
b11011110001 !
b11011110001 )
b11011110001 (
b11011110001 "
b110111100011011110001001 $
b110111100011011110001001 '
#82000
b10101110001 !
b10101110001 )
b10101110001 (
b10101110001 "
b101011100011001001001001 $
b101011100011001001001001 '
#83000
b100011001 !
b100011001 )
b100011001 (
b100011001 "
b1000110011111011010000 $
b1000110011111011010000 '
#84000
b11111111111111111111111111110110 !
b11111111111111111111111111110110 )
b111111110110 (
b11111111111111111111111111110110 "
b1111111101100000011010111 $
b1111111101100000011010111 '
#85000
b11000111111 !
b11000111111 )
b11000111111 (
b11000111111 "
b110001111111110001010001 $
b110001111111110001010001 '
#86000
b11111111111111111111100100001001 !
b11111111111111111111100100001001 )
b100100001001 (
b11111111111111111111100100001001 "
b1001000010010111110010110 $
b1001000010010111110010110 '
#87000
b11101011 !
b11101011 )
b11101011 (
b11101011 "
b111010111111100001100 $
b111010111111100001100 '
#88000
b11111111111111111111100101100110 !
b11111111111111111111100101100110 )
b100101100110 (
b11111111111111111111100101100110 "
b1001011001100111011000010 $
b1001011001100111011000010 '
#89000
b1010111111 !
b1010111111 )
b1010111111 (
b1010111111 "
b10101111110110111001000 $
b10101111110110111001000 '
#90000
b11111111111111111111110000010010 !
b11111111111111111111110000010010 )
b110000010010 (
b11111111111111111111110000010010 "
b1100000100101101001110111 $
b1100000100101101001110111 '
#91000
b11110010111 !
b11110010111 )
b11110010111 (
b11110010111 "
b111100101110110100111101 $
b111100101110110100111101 '
#92000
b11111111111111111111100001100110 !
b11111111111111111111100001100110 )
b100001100110 (
b11111111111111111111100001100110 "
b1000011001101101100010010 $
b1000011001101101100010010 '
#93000
b11111111111111111111100000101000 !
b11111111111111111111100000101000 )
b100000101000 (
b11111111111111111111100000101000 "
b1000001010000000001111110 $
b1000001010000000001111110 '
#94000
b11100101100 !
b11100101100 )
b11100101100 (
b11100101100 "
b111001011000000101101101 $
b111001011000000101101101 '
#95000
b11011001111 !
b11011001111 )
b11011001111 (
b11011001111 "
b110110011110011100111001 $
b110110011110011100111001 '
#96000
b11111111111111111111111010010100 !
b11111111111111111111111010010100 )
b111010010100 (
b11111111111111111111111010010100 "
b1110100101000111100011111 $
b1110100101000111100011111 '
#97000
b11111111111111111111111101011111 !
b11111111111111111111111101011111 )
b111101011111 (
b11111111111111111111111101011111 "
b1111010111111011011010011 $
b1111010111111011011010011 '
#98000
b11011001001 !
b11011001001 )
b11011001001 (
b11011001001 "
b110110010010111110000101 $
b110110010010111110000101 '
#99000
b10100100 !
b10100100 )
b10100100 (
b10100100 "
b101001000100001111000 $
b101001000100001111000 '
#100000
b11111111111111111111111011010010 !
b11111111111111111111111011010010 )
b111011010010 (
b11111111111111111111111011010010 "
b1110110100101100101011011 $
b1110110100101100101011011 '
#101000
b10001011010 !
b10001011010 )
b10001011010 (
b10001011010 "
b100010110100101101001001 $
b100010110100101101001001 '
#102000
b11111111111111111111111110010101 !
b11111111111111111111111110010101 )
b111110010101 (
b11111111111111111111111110010101 "
b1111100101010111000111111 $
b1111100101010111000111111 '
#103000
b11111111111111111111100001100101 !
b11111111111111111111100001100101 )
b100001100101 (
b11111111111111111111100001100101 "
b1000011001010111100101010 $
b1000011001010111100101010 '
#104000
b10101011 !
b10101011 )
b10101011 (
b10101011 "
b101010110001101011000 $
b101010110001101011000 '
#105000
b11111111111111111111100111111001 !
b11111111111111111111100111111001 )
b100111111001 (
b11111111111111111111100111111001 "
b1001111110011100010000110 $
b1001111110011100010000110 '
#106000
b11111111111111111111100011010000 !
b11111111111111111111100011010000 )
b100011010000 (
b11111111111111111111100011010000 "
b1000110100000110010001110 $
b1000110100000110010001110 '
#107000
b101111111 !
b101111111 )
b101111111 (
b101111111 "
b1011111111001010011100 $
b1011111111001010011100 '
#108000
b11111111111111111111100110101100 !
b11111111111111111111100110101100 )
b100110101100 (
b11111111111111111111100110101100 "
b1001101011001100111111010 $
b1001101011001100111111010 '
#109000
b11111111111111111111101111101101 !
b11111111111111111111101111101101 )
b101111101101 (
b11111111111111111111101111101101 "
b1011111011011110000100110 $
b1011111011011110000100110 '
#110000
b11111111111111111111110010110000 !
b11111111111111111111110010110000 )
b110010110000 (
b11111111111111111111110010110000 "
b1100101100001011101110011 $
b1100101100001011101110011 '
#111000
b11111111111111111111110001011101 !
b11111111111111111111110001011101 )
b110001011101 (
b11111111111111111111110001011101 "
b1100010111011010010100011 $
b1100010111011010010100011 '
#112000
b11111111111111111111110011001101 !
b11111111111111111111110011001101 )
b110011001101 (
b11111111111111111111110011001101 "
b1100110011010100000101111 $
b1100110011010100000101111 '
#113000
b11111111111111111111111010010100 !
b11111111111111111111111010010100 )
b111010010100 (
b11111111111111111111111010010100 "
b1110100101001001010110011 $
b1110100101001001010110011 '
#114000
b11111111111111111111111011000010 !
b11111111111111111111111011000010 )
b111011000010 (
b11111111111111111111111011000010 "
b1110110000101011001011111 $
b1110110000101011001011111 '
#115000
b101001000 !
b101001000 )
b101001000 (
b101001000 "
b1010010000110101000100 $
b1010010000110101000100 '
#116000
b11111111111111111111111111000111 !
b11111111111111111111111111000111 )
b111111000111 (
b11111111111111111111111111000111 "
b1111110001111110111110111 $
b1111110001111110111110111 '
#117000
b11111111111111111111110011011001 !
b11111111111111111111110011011001 )
b110011011001 (
b11111111111111111111110011011001 "
b1100110110011011011001011 $
b1100110110011011011001011 '
#118000
b11111111111111111111100001001000 !
b11111111111111111111100001001000 )
b100001001000 (
b11111111111111111111100001001000 "
b1000010010001101011100110 $
b1000010010001101011100110 '
#119000
b11111111111111111111100101000110 !
b11111111111111111111100101000110 )
b100101000110 (
b11111111111111111111100101000110 "
b1001010001101101101011010 $
b1001010001101101101011010 '
#120000
b11001111110 !
b11001111110 )
b11001111110 (
b11001111110 "
b110011111100000100101001 $
b110011111100000100101001 '
#121000
b10000010111 !
b10000010111 )
b10000010111 (
b10000010111 "
b100000101110001011101101 $
b100000101110001011101101 '
#122000
b11111111111111111111101010011011 !
b11111111111111111111101010011011 )
b101010011011 (
b11111111111111111111101010011011 "
b1010100110110110011011010 $
b1010100110110110011011010 '
#123000
b10011111101 !
b10011111101 )
b10011111101 (
b10011111101 "
b100111111011011001100101 $
b100111111011011001100101 '
#124000
b10001010111 !
b10001010111 )
b10001010111 (
b10001010111 "
b100010101110001010110101 $
b100010101110001010110101 '
#125000
b11111111111111111111110111110100 !
b11111111111111111111110111110100 )
b110111110100 (
b11111111111111111111110111110100 "
b1101111101001010011011111 $
b1101111101001010011011111 '
#126000
b11110001000 !
b11110001000 )
b11110001000 (
b11110001000 "
b111100010001100101111001 $
b111100010001100101111001 '
#127000
b110001111 !
b110001111 )
b110001111 (
b110001111 "
b1100011111111101000100 $
b1100011111111101000100 '
#128000
b1110100000 !
b1110100000 )
b1110100000 (
b1110100000 "
b11101000000110011010000 $
b11101000000110011010000 '
#129000
b11111111111111111111100001001000 !
b11111111111111111111100001001000 )
b100001001000 (
b11111111111111111111100001001000 "
b1000010010000101100101010 $
b1000010010000101100101010 '
#130000
b11111111111111111111111110110101 !
b11111111111111111111111110110101 )
b111110110101 (
b11111111111111111111111110110101 "
b1111101101010110110101011 $
b1111101101010110110101011 '
#131000
b11111111111111111111101101111110 !
b11111111111111111111101101111110 )
b101101111110 (
b11111111111111111111101101111110 "
b1011011111100111100001110 $
b1011011111100111100001110 '
#132000
b1011101101 !
b1011101101 )
b1011101101 (
b1011101101 "
b10111011010110111011100 $
b10111011010110111011100 '
#133000
b11111111111111111111101011110101 !
b11111111111111111111101011110101 )
b101011110101 (
b11111111111111111111101011110101 "
b1010111101011110010011010 $
b1010111101011110010011010 '
#134000
b11011111011 !
b11011111011 )
b11011111011 (
b11011111011 "
b110111110111001011111101 $
b110111110111001011111101 '
#135000
b11111111111111111111111110001000 !
b11111111111111111111111110001000 )
b111110001000 (
b11111111111111111111111110001000 "
b1111100010000001011000011 $
b1111100010000001011000011 '
#136000
b11111111111111111111100001110111 !
b11111111111111111111100001110111 )
b100001110111 (
b11111111111111111111100001110111 "
b1000011101110110101010110 $
b1000011101110110101010110 '
#137000
b11111111111111111111101111001111 !
b11111111111111111111101111001111 )
b101111001111 (
b11111111111111111111101111001111 "
b1011110011110100101001110 $
b1011110011110100101001110 '
#138000
b11111111111111111111111011001011 !
b11111111111111111111111011001011 )
b111011001011 (
b11111111111111111111111011001011 "
b1110110010111011001100111 $
b1110110010111011001100111 '
#139000
b11111111111111111111100110001001 !
b11111111111111111111100110001001 )
b100110001001 (
b11111111111111111111100110001001 "
b1001100010011010000001010 $
b1001100010011010000001010 '
#140000
b11111111111111111111101101111101 !
b11111111111111111111101101111101 )
b101101111101 (
b11111111111111111111101101111101 "
b1011011111011100110110110 $
b1011011111011100110110110 '
#141000
b1110100 !
b1110100 )
b1110100 (
b1110100 "
b11101000101000111000 $
b11101000101000111000 '
#142000
b11010001100 !
b11010001100 )
b11010001100 (
b11010001100 "
b110100011000011101111001 $
b110100011000011101111001 '
#143000
b101011110 !
b101011110 )
b101011110 (
b101011110 "
b1010111100010010111000 $
b1010111100010010111000 '
#144000
b1110100101 !
b1110100101 )
b1110100101 (
b1110100101 "
b11101001011111110010100 $
b11101001011111110010100 '
#145000
b11111111111111111111111000110010 !
b11111111111111111111111000110010 )
b111000110010 (
b11111111111111111111111000110010 "
b1110001100101110110010011 $
b1110001100101110110010011 '
#146000
b111111001 !
b111111001 )
b111111001 (
b111111001 "
b1111110010110000000100 $
b1111110010110000000100 '
#147000
b10110111110 !
b10110111110 )
b10110111110 (
b10110111110 "
b101101111100101001011001 $
b101101111100101001011001 '
#148000
b11111111111111111111111001011011 !
b11111111111111111111111001011011 )
b111001011011 (
b11111111111111111111111001011011 "
b1110010110110100111011011 $
b1110010110110100111011011 '
#149000
b11111100110 !
b11111100110 )
b11111100110 (
b11111100110 "
b111111001101111001001101 $
b111111001101111001001101 '
#150000
b10110000101 !
b10110000101 )
b10110000101 (
b10110000101 "
b101100001011011111011001 $
b101100001011011111011001 '
#151000
b10100100001 !
b10100100001 )
b10100100001 (
b10100100001 "
b101001000010011001101101 $
b101001000010011001101101 '
#152000
b11111111111111111111101000101111 !
b11111111111111111111101000101111 )
b101000101111 (
b11111111111111111111101000101111 "
b1010001011110001001110110 $
b1010001011110001001110110 '
#153000
b11111111111111111111100111011010 !
b11111111111111111111100111011010 )
b100111011010 (
b11111111111111111111100111011010 "
b1001110110100100111001010 $
b1001110110100100111001010 '
#154000
b11111111111111111111100010111001 !
b11111111111111111111100010111001 )
b100010111001 (
b11111111111111111111100010111001 "
b1000101110010110110110110 $
b1000101110010110110110110 '
#155000
b10010011011 !
b10010011011 )
b10010011011 (
b10010011011 "
b100100110111000110010101 $
b100100110111000110010101 '
#156000
b11111111111111111111100000111000 !
b11111111111111111111100000111000 )
b100000111000 (
b11111111111111111111100000111000 "
b1000001110001101001000110 $
b1000001110001101001000110 '
#157000
b1110100100 !
b1110100100 )
b1110100100 (
b1110100100 "
b11101001001101100000100 $
b11101001001101100000100 '
#158000
b11111111111111111111111010010011 !
b11111111111111111111111010010011 )
b111010010011 (
b11111111111111111111111010010011 "
b1110100100110000111110111 $
b1110100100110000111110111 '
#159000
b10011000000 !
b10011000000 )
b10011000000 (
b10011000000 "
b100110000000011101101001 $
b100110000000011101101001 '
#160000
b1101110101 !
b1101110101 )
b1101110101 (
b1101110101 "
b11011101011101010110100 $
b11011101011101010110100 '
#161000
b1100 !
b1100 )
b1100 (
b1100 "
b11000110110001000 $
b11000110110001000 '
#162000
b1111100110 !
b1111100110 )
b1111100110 (
b1111100110 "
b11111001101100100101000 $
b11111001101100100101000 '
#163000
b10010000000 !
b10010000000 )
b10010000000 (
b10010000000 "
b100100000000010000101101 $
b100100000000010000101101 '
#164000
b11111111111111111111111000101001 !
b11111111111111111111111000101001 )
b111000101001 (
b11111111111111111111111000101001 "
b1110001010011000011000111 $
b1110001010011000011000111 '
#165000
b11111111111111111111101011100100 !
b11111111111111111111101011100100 )
b101011100100 (
b11111111111111111111101011100100 "
b1010111001001110000101110 $
b1010111001001110000101110 '
#166000
b1110111111 !
b1110111111 )
b1110111111 (
b1110111111 "
b11101111110010000001000 $
b11101111110010000001000 '
#167000
b1000001010 !
b1000001010 )
b1000001010 (
b1000001010 "
b10000010100010100011100 $
b10000010100010100011100 '
#168000
b10100111101 !
b10100111101 )
b10100111101 (
b10100111101 "
b101001111010011011111101 $
b101001111010011011111101 '
#169000
b10011110000 !
b10011110000 )
b10011110000 (
b10011110000 "
b100111100000011100101001 $
b100111100000011100101001 '
#170000
b110111100 !
b110111100 )
b110111100 (
b110111100 "
b1101111001000000011100 $
b1101111001000000011100 '
#171000
b11111111111111111111100110101011 !
b11111111111111111111100110101011 )
b100110101011 (
b11111111111111111111100110101011 "
b1001101010110011110000110 $
b1001101010110011110000110 '
#172000
b11111111111111111111100110100000 !
b11111111111111111111100110100000 )
b100110100000 (
b11111111111111111111100110100000 "
b1001101000000100011011010 $
b1001101000000100011011010 '
#173000
b10110111110 !
b10110111110 )
b10110111110 (
b10110111110 "
b101101111100011000111101 $
b101101111100011000111101 '
#174000
b11111111111111111111101001110101 !
b11111111111111111111101001110101 )
b101001110101 (
b11111111111111111111101001110101 "
b1010011101010011101100110 $
b1010011101010011101100110 '
#175000
b1010101110 !
b1010101110 )
b1010101110 (
b1010101110 "
b10101011100010001110000 $
b10101011100010001110000 '
#176000
b11111111111111111111111110101000 !
b11111111111111111111111110101000 )
b111110101000 (
b11111111111111111111111110101000 "
b1111101010000010001110011 $
b1111101010000010001110011 '
#177000
b11111111111111111111101110001100 !
b11111111111111111111101110001100 )
b101110001100 (
b11111111111111111111101110001100 "
b1011100011001100110111010 $
b1011100011001100110111010 '
#178000
b11111111111111111111100111010101 !
b11111111111111111111100111010101 )
b100111010101 (
b11111111111111111111100111010101 "
b1001110101011001101011110 $
b1001110101011001101011110 '
#179000
b11111111111111111111101000111011 !
b11111111111111111111101000111011 )
b101000111011 (
b11111111111111111111101000111011 "
b1010001110111100111111010 $
b1010001110111100111111010 '
#180000
b10001110000 !
b10001110000 )
b10001110000 (
b10001110000 "
b100011100000010111010101 $
b100011100000010111010101 '
#181000
b11111111111111111111100100100111 !
b11111111111111111111100100100111 )
b100100100111 (
b11111111111111111111100100100111 "
b1001001001111011000011010 $
b1001001001111011000011010 '
#182000
b11110000000 !
b11110000000 )
b11110000000 (
b11110000000 "
b111100000000000010111001 $
b111100000000000010111001 '
#183000
b11111111111111111111110000111011 !
b11111111111111111111110000111011 )
b110000111011 (
b11111111111111111111110000111011 "
b1100001110110000100110111 $
b1100001110110000100110111 '
#184000
b11111111111111111111100100111001 !
b11111111111111111111100100111001 )
b100100111001 (
b11111111111111111111100100111001 "
b1001001110011011110010110 $
b1001001110011011110010110 '
#185000
b111001001 !
b111001001 )
b111001001 (
b111001001 "
b1110010010000111000000 $
b1110010010000111000000 '
#186000
b11111111111111111111100100101100 !
b11111111111111111111100100101100 )
b100100101100 (
b11111111111111111111100100101100 "
b1001001011001111100100110 $
b1001001011001111100100110 '
#187000
b11111111111111111111101000110000 !
b11111111111111111111101000110000 )
b101000110000 (
b11111111111111111111101000110000 "
b1010001100001101010110110 $
b1010001100001101010110110 '
#188000
b10011001100 !
b10011001100 )
b10011001100 (
b10011001100 "
b100110011000001101111101 $
b100110011000001101111101 '
#189000
b1011111000 !
b1011111000 )
b1011111000 (
b1011111000 "
b10111110000111111011100 $
b10111110000111111011100 '
