src/alu.sv
module alu #(parameter DATA_WIDTH = 32) (
    input wire [DATA_WIDTH-1:0] a,
    input wire [DATA_WIDTH-1:0] b,
    input wire [2:0] alu_op, // ALU operation code

    output reg [DATA_WIDTH-1:0] result,
    output wire zero, // zero flag
    output wire carry, // carry flag
    output wire overflow // overflow flag
);

  typedef enum logic [2:0] {
    ADD = 3'b000 // Load Word
  } alu_ops_e;

  always_comb begin
    case (alu_op)
      ADD: result = a + b;
      default: result = '0; // Default case to avoid latches
    endcase
  end

  assign zero = (result == 0);

endmodule

tests/test_alu.sv
`timescale 1ns/1ps

module test_alu;

  localparam int DATA_WIDTH = 32;
  reg test_failed;

  task finish;
    begin
      if (test_failed) begin
        $display("Test failed!");
      end else begin
        $display("Test passed!");
      end
      $finish; // End simulation
    end
  endtask

  // dut io
  reg [DATA_WIDTH-1:0] a;
  reg [DATA_WIDTH-1:0] b;
  reg [2:0] alu_op; // ALU operation code

  wire [DATA_WIDTH-1:0] result;
  wire zero; // zero flag
  wire carry; // carry flag
  wire overflow; // overflow flag

  // dut instantiation
  alu #(
    .DATA_WIDTH(DATA_WIDTH)
  ) dut (
    .a(a),
    .b(b),
    .alu_op(alu_op),
    .result(result),
    .zero(zero),
    .carry(carry),
    .overflow(overflow)
  );

  // test cases
  initial begin
    $dumpfile("./tests/results/test_alu.vcd");
    $dumpvars(0, test_alu);

    repeat (1000) begin
      a = {$random};
      b = {$random};
      alu_op = dut.ADD; // Load Word operation

      #1; // wait for result

      if (result !== (a + b)) begin
        test_failed = 1;
        $display("[%0t] error: expected result 0x%h, got 0x%h", $time, (a + b), result);
      end else begin
        $display("[%0t] OK: result is 0x%h", $time, result);
      end
    end

    finish; // End simulation
  end

endmodule

tests/results/test_alu.vcd
$date
	Sun Aug 17 08:47:04 2025
$end
$version
	Icarus Verilog
$end
$timescale
	1ps
$end
$scope module test_alu $end
$var wire 1 ! carry $end
$var wire 1 " overflow $end
$var wire 1 # zero $end
$var wire 32 $ result [31:0] $end
$var reg 32 % a [31:0] $end
$var reg 3 & alu_op [2:0] $end
$var reg 32 ' b [31:0] $end
$var reg 1 ( test_failed $end
$scope module dut $end
$var wire 32 ) a [31:0] $end
$var wire 3 * alu_op [2:0] $end
$var wire 32 + b [31:0] $end
$var wire 1 ! carry $end
$var wire 1 " overflow $end
$var wire 1 # zero $end
$var reg 32 , result [31:0] $end
$upscope $end
$scope task finish $end
$upscope $end
$upscope $end
$enddefinitions $end
#0
$dumpvars
b11010010100111101001001110100101 ,
b11000000100010010101111010000001 +
b0 *
b10010000101010011010100100100 )
x(
b11000000100010010101111010000001 '
b0 &
b10010000101010011010100100100 %
b11010010100111101001001110100101 $
0#
z"
z!
$end
#1000
b110110011101010010110001101100 $
b110110011101010010110001101100 ,
b10110001111100000101011001100011 '
b10110001111100000101011001100011 +
b10000100100001001101011000001001 %
b10000100100001001101011000001001 )
#2000
b1001101100110010001010010011010 $
b1001101100110010001010010011010 ,
b1000110110111111001100110001101 '
b1000110110111111001100110001101 +
b110101110010111101100001101 %
b110101110010111101100001101 )
#3000
b111011111110011101011001110111 $
b111011111110011101011001110111 ,
b10001001001101110101001000010010 '
b10001001001101110101001000010010 +
b10110010110000101000010001100101 %
b10110010110000101000010001100101 )
#4000
b111110010111011000000001110 $
b111110010111011000000001110 ,
b110110101111100110100001101 '
b110110101111100110100001101 +
b111100111110001100000001 %
b111100111110001100000001 )
#5000
b1011001101100011011111010110011 $
b1011001101100011011111010110011 ,
b11110100011011100110100111101 '
b11110100011011100110100111101 +
b111011001000111111000101110110 %
b111011001000111111000101110110 )
#6000
b10111101000000100100111101111001 $
b10111101000000100100111101111001 ,
b1000110001011011111011110001100 '
b1000110001011011111011110001100 +
b1110110110101000101011111101101 %
b1110110110101000101011111101101 )
#7000
b1100000001101010000111010111111 $
b1100000001101010000111010111111 ,
b11100011001101110010010011000110 '
b11100011001101110010010011000110 +
b1111100111111011110100111111001 %
b1111100111111011110100111111001 )
#8000
b10111000000010110101011101101111 $
b10111000000010110101011101101111 ,
b11010101000100111101001010101010 '
b11010101000100111101001010101010 +
b11100010111101111000010011000101 %
b11100010111101111000010011000101 )
#9000
b101110100000100110101001011100 $
b101110100000100110101001011100 ,
b10111011110100100111001001110111 '
b10111011110100100111001001110111 +
b1110010101011111111011111100101 %
b1110010101011111111011111100101 )
#10000
b11010001000111111011000110100001 $
b11010001000111111011000110100001 ,
b1000111111011001101101110001111 '
b1000111111011001101101110001111 +
b10001001001100101101011000010010 %
b10001001001100101101011000010010 )
#11000
b1100000101001110000000011000000 $
b1100000101001110000000011000000 ,
b11100111011101101001011011001110 '
b11100111011101101001011011001110 +
b1111001001100000110100111110010 %
b1111001001100000110100111110010 )
#12000
b11010110110010101100100110101101 $
b11010110110010101100100110101101 ,
b11100010110010100100111011000101 '
b11100010110010100100111011000101 +
b11110100000000000111101011101000 %
b11110100000000000111101011101000 )
#13000
b1100111001100111001000011001 $
b1100111001100111001000011001 ,
b11011110100011100010100010111101 '
b11011110100011100010100010111101 +
b101110010110000100100101011100 %
b101110010110000100100101011100 )
#14000
b1001001010100100111111010010010 $
b1001001010100100111111010010010 ,
b10110010101001110010011001100101 '
b10110010101001110010011001100101 +
b10010110101010110101100000101101 %
b10010110101010110101100000101101 )
#15000
b10110111011000101110100101101101 $
b10110111011000101110100101101101 ,
b101011100111000011100001010 '
b101011100111000011100001010 +
b10110001111011110110001001100011 %
b10110001111011110110001001100011 )
#16000
b11010000100111110100001110100000 $
b11010000100111110100001110100000 ,
b10000011001000010000100100000 '
b10000011001000010000100100000 +
b11000000001110110010001010000000 %
b11000000001110110010001010000000 )
#17000
b100100010001010001001001000111 $
b100100010001010001001001000111 ,
b11001110110011001100110010011101 '
b11001110110011001100110010011101 +
b1010101011110000100010110101010 %
b1010101011110000100010110101010 )
#18000
b1010100101000111111011010101001 $
b1010100101000111111011010101001 ,
b10001001100000111011100000010011 '
b10001001100000111011100000010011 +
b11001011001000000011111010010110 %
b11001011001000000011111010010110 )
#19000
b110000011001000000111001100000 $
b110000011001000000111001100000 ,
b10101001101001111101011001010011 '
b10101001101001111101011001010011 +
b10000110101111000011100000001101 %
b10000110101111000011100000001101 )
#20000
b100000010001100000100001000000 $
b100000010001100000100001000000 ,
b11101010101001100010101011010101 '
b11101010101001100010101011010101 +
b110101100111111101110101101011 %
b110101100111111101110101101011 )
#21000
b1011000011011011000100010110000 $
b1011000011011011000100010110000 ,
b11010111010101100011111010101110 '
b11010111010101100011111010101110 +
b10000001000101110100101000000010 %
b10000001000101110100101000000010 )
#22000
b11110110110001010101101111101100 $
b11110110110001010101101111101100 ,
b11100111110001010111001011001111 '
b11100111110001010111001011001111 +
b1110111111111110100100011101 %
b1110111111111110100100011101 )
#23000
b10110100011011010111000101101 $
b10110100011011010111000101101 ,
b101000010010110010100001010 '
b101000010010110010100001010 +
b10001100001000100100100100011 %
b10001100001000100100100100011 )
#24000
b10000011101001000101011100000110 $
b10000011101001000101011100000110 ,
b10011110001100010100110000111100 '
b10011110001100010100110000111100 +
b11100101011100110000101011001010 %
b11100101011100110000101011001010 )
#25000
b10111110100101110001111101111100 $
b10111110100101110001111101111100 ,
b1000101001011100110000110001010 '
b1000101001011100110000110001010 +
b1111001011010001011110111110010 %
b1111001011010001011110111110010 )
#26000
b1101000011111110100000011001 $
b1101000011111110100000011001 ,
b11101100010010110011010011011000 '
b11101100010010110011010011011000 +
b100000110001001011001101000001 %
b100000110001001011001101000001 )
#27000
b101010110000011000000001 $
b101010110000011000000001 ,
b11000100100010100001001010001001 '
b11000100100010100001001010001001 +
b111100001000001111001101111000 %
b111100001000001111001101111000 )
#28000
b11010000110001110111001110100001 $
b11010000110001110111001110100001 ,
b1011011000000100110010110110110 '
b1011011000000100110010110110110 +
b1110101110001010000110111101011 %
b1110101110001010000110111101011 )
#29000
b10111010011000010000110101110100 $
b10111010011000010000110101110100 ,
b1010111000101010001001110101110 '
b1010111000101010001001110101110 +
b1100011010010111111100111000110 %
b1100011010010111111100111000110 )
#30000
b11110011100001001101111111100110 $
b11110011100001001101111111100110 ,
b10101000011111101110100101010 '
b10101000011111101110100101010 +
b11011110011101010000001010111100 %
b11011110011101010000001010111100 )
#31000
b111110011011110101100001111100 $
b111110011011110101100001111100 ,
b10111000100101111011111001110001 '
b10111000100101111011111001110001 +
b10000101110101111001101000001011 %
b10000101110101111001101000001011 )
#32000
b1101010111001001001011011010100 $
b1101010111001001001011011010100 ,
b100111111100100101010101001111 '
b100111111100100101010101001111 +
b1000010111100100100000110000101 %
b1000010111100100100000110000101 )
#33000
b10111010110100101001001101110101 $
b10111010110100101001001101110101 ,
b11101000001100011001100111010 '
b11101000001100011001100111010 +
b10011101110011000110000000111011 %
b10011101110011000110000000111011 )
#34000
b11001001110011010111110110010011 $
b11001001110011010111110110010011 ,
b1010101010100100101100010101 '
b1010101010100100101100010101 +
b10111111001000110011001001111110 %
b10111111001000110011001001111110 )
#35000
b11100101011101011110011111001010 $
b11100101011101011110011111001010 ,
b1101100100111000100101111011001 '
b1101100100111000100101111011001 +
b1111000110110011001101111110001 %
b1111000110110011001101111110001 )
#36000
b1010111010110010000001010101110 $
b1010111010110010000001010101110 ,
b100110001101011111101101001100 '
b100110001101011111101101001100 +
b110001001000110000011101100010 %
b110001001000110000011101100010 )
#37000
b10010111010110101111011100101110 $
b10010111010110101111011100101110 ,
b1000111101110011010000110001111 '
b1000111101110011010000110001111 +
b1001111101000010101010110011111 %
b1001111101000010101010110011111 )
#38000
b1011000001110110000101010101111 $
b1011000001110110000101010101111 ,
b11011011110011010110000010110111 '
b11011011110011010110000010110111 +
b1111100011011011010100111111000 %
b1111100011011011010100111111000 )
#39000
b1111110010000011110101011111011 $
b1111110010000011110101011111011 ,
b10101110011111011001010001011100 '
b10101110011111011001010001011100 +
b11001111110001000101011010011111 %
b11001111110001000101011010011111 )
#40000
b11110010101010011111011111100100 $
b11110010101010011111011111100100 ,
b1000100110111100011011110001001 '
b1000100110111100011011110001001 +
b10101101110010111100000001011011 %
b10101101110010111100000001011011 )
#41000
b10001100110100010111000100011001 $
b10001100110100010111000100011001 ,
b11101000001000110011111011010000 '
b11101000001000110011111011010000 +
b10100100101011100011001001001001 %
b10100100101011100011001001001001 )
#42000
b10010100110001101011110100101000 $
b10010100110001101011110100101000 ,
b10101000110001111111110001010001 '
b10101000110001111111110001010001 +
b11101011111111101100000011010111 %
b11101011111111101100000011010111 )
#43000
b1010001001111101010111010100010 $
b1010001001111101010111010100010 ,
b110000111010111111100001100 '
b110000111010111111100001100 +
b1001011001000010010111110010110 %
b1001011001000010010111110010110 )
#44000
b1000101100001001011110010001010 $
b1000101100001001011110010001010 ,
b1100100010101111110110111001000 '
b1100100010101111110110111001000 +
b11100001001011001100111011000010 %
b11100001001011001100111011000010 )
#45000
b11011010011101010100011110110100 $
b11011010011101010100011110110100 ,
b11110111100101110110100111101 '
b11110111100101110110100111101 +
b10111011100000100101101001110111 %
b10111011100000100101101001110111 )
#46000
b11001000000100011101101110010000 $
b11001000000100011101101110010000 ,
b10111111000001010000000001111110 '
b10111111000001010000000001111110 +
b1001000011001101101100010010 %
b1001000011001101101100010010 )
#47000
b1010011101111110110100010100110 $
b1010011101111110110100010100110 ,
b11100110110011110011100111001 '
b11100110110011110011100111001 +
b110110111001011000000101101101 %
b110110111001011000000101101101 )
#48000
b11111001101111101000010111110010 $
b11111001101111101000010111110010 ,
b11101001111010111111011011010011 '
b11101001111010111111011011010011 +
b1111110100101000111100011111 %
b1111110100101000111100011111 )
#49000
b11111110111011011011011111111101 $
b11111110111011011011011111111101 ,
b10111100000101001000100001111000 '
b10111100000101001000100001111000 +
b1000010110110010010111110000101 %
b1000010110110010010111110000101 )
#50000
b1010010011001011010010010100100 $
b1010010011001011010010010100100 ,
b100100100010110100101101001001 '
b100100100010110100101101001001 +
b101101110110100101100101011011 %
b101101110110100101100101011011 )
#51000
b10110100111111110101110101101001 $
b10110100111111110101110101101001 ,
b10101000011001010111100101010 '
b10101000011001010111100101010 +
b10011111111100101010111000111111 %
b10011111111100101010111000111111 )
#52000
b11101111010101001001101111011110 $
b11101111010101001001101111011110 ,
b11000011001111110011100010000110 '
b11000011001111110011100010000110 +
b101100000101010110001101011000 %
b101100000101010110001101011000 )
#53000
b10010101010010011111111100101010 $
b10010101010010011111111100101010 ,
b11001110001011111111001010011100 '
b11001110001011111111001010011100 +
b11000111000110100000110010001110 %
b11000111000110100000110010001110 )
#54000
b10000101100110101011000100000 $
b10000101100110101011000100000 ,
b10010011011111011011110000100110 '
b10010011011111011011110000100110 +
b1111101001101011001100111111010 %
b1111101001101011001100111111010 )
#55000
b1011001000011100110000010110 $
b1011001000011100110000010110 ,
b11010001100010111011010010100011 '
b11010001100010111011010010100011 +
b111001100101100001011101110011 %
b111001100101100001011101110011 )
#56000
b1110001011011000011101011100010 $
b1110001011011000011101011100010 ,
b11011001110100101001001010110011 '
b11011001110100101001001010110011 +
b10010111100110011010100000101111 %
b10010111100110011010100000101111 )
#57000
b11010010000000010110001110100011 $
b11010010000000010110001110100011 ,
b100010001010010000110101000100 '
b100010001010010000110101000100 +
b10101111110110000101011001011111 %
b10101111110110000101011001011111 )
#58000
b1100001100101000011010011000010 $
b1100001100101000011010011000010 ,
b11100101100110110011011011001011 '
b11100101100110110011011011001011 +
b1111011111110001111110111110111 %
b1111011111110001111110111110111 )
#59000
b100000001100011111011001000000 $
b100000001100011111011001000000 ,
b101101001010001101101101011010 '
b101101001010001101101101011010 +
b11110011000010010001101011100110 %
b11110011000010010001101011100110 )
#60000
b1011010100101010010000010110 $
b1011010100101010010000010110 ,
b11110110100000101110001011101101 '
b11110110100000101110001011101101 +
b10100110011111100000100101001 %
b10100110011111100000100101001 )
#61000
b10011111111100110010001100111111 $
b10011111111100110010001100111111 ,
b10110010100111111011011001100101 '
b10110010100111111011011001100101 +
b11101101010100110110110011011010 %
b11101101010100110110110011011010 )
#62000
b11001010010010010111011110010100 $
b11001010010010010111011110010100 ,
b11101111101111101001010011011111 '
b11101111101111101001010011011111 +
b11011010100010101110001010110101 %
b11011010100010101110001010110101 )
#63000
b1011111001000110001100010111101 $
b1011111001000110001100010111101 ,
b100010001100011111111101000100 '
b100010001100011111111101000100 +
b111100111100010001100101111001 %
b111100111100010001100101111001 )
#64000
b11111101011111010001011111111010 $
b11111101011111010001011111111010 ,
b10101000010010000101100101010 '
b10101000010010000101100101010 +
b11101000011101000000110011010000 %
b11101000011101000000110011010000 )
#65000
b1011101011001100111110010111001 $
b1011101011001100111110010111001 ,
b111011011111100111100001110 '
b111011011111100111100001110 +
b1010101111101101010110110101011 %
b1010101111101101010110110101011 )
#66000
b111011101111000110101001110110 $
b111011101111000110101001110110 ,
b11001101010111101011110010011010 '
b11001101010111101011110010011010 +
b1101110010111011010110111011100 %
b1101110010111011010110111011100 )
#67000
b11100000110100000111010111000000 $
b11100000110100000111010111000000 ,
b11100001111100010000001011000011 '
b11100001111100010000001011000011 +
b11111110110111110111001011111101 %
b11111110110111110111001011111101 )
#68000
b1010010100010001101011010100100 $
b1010010100010001101011010100100 ,
b100111011110011110100101001110 '
b100111011110011110100101001110 +
b101011000011101110110101010110 %
b101011000011101110110101010110 )
#69000
b111001000010101010101001110001 $
b111001000010101010101001110001 ,
b10000101001100010011010000001010 '
b10000101001100010011010000001010 +
b10110011110110010111011001100111 %
b10110011110110010111011001100111 )
#70000
b11110111011111100100001111101110 $
b11110111011111100100001111101110 ,
b10011100000011101000101000111000 '
b10011100000011101000101000111000 +
b1011011011011111011100110110110 %
b1011011011011111011100110110110 )
#71000
b11000111111010100110000110001 $
b11000111111010100110000110001 ,
b11011100001010111100010010111000 '
b11011100001010111100010010111000 +
b111100110100011000011101111001 %
b111100110100011000011101111001 )
#72000
b10010100001110110001110100100111 $
b10010100001110110001110100100111 ,
b1001001110001100101110110010011 '
b1001001110001100101110110010011 +
b1001010011101001011111110010100 %
b1001010011101001011111110010100 )
#73000
b101110111101101111011001011101 $
b101110111101101111011001011101 ,
b10101100101101111100101001011001 '
b10101100101101111100101001011001 +
b10000010001111110010110000000100 %
b10000010001111110010110000000100 )
#74000
b10100110010000100100000101000 $
b10100110010000100100000101000 ,
b10100110111111001101111001001101 '
b10100110111111001101111001001101 +
b1101101110010110110100111011011 %
b1101101110010110110100111011011 )
#75000
b100011010101001101111001000110 $
b100011010101001101111001000110 ,
b10110110101001000010011001101101 '
b10110110101001000010011001101101 +
b1101100101100001011011111011001 %
b1101100101100001011011111011001 )
#76000
b100000100000010010110001000000 $
b100000100000010010110001000000 ,
b1100101001110110100100111001010 '
b1100101001110110100100111001010 +
b10111011010001011110001001110110 %
b10111011010001011110001001110110 )
#77000
b10100101101010101001111101001011 $
b10100101101010101001111101001011 ,
b1001010100100110111000110010101 '
b1001010100100110111000110010101 +
b1011011000101110010110110110110 %
b1011011000101110010110110110110 )
#78000
b10100101011110111011010101001010 $
b10100101011110111011010101001010 ,
b10011101001001101100000100 '
b10011101001001101100000100 +
b10100011000001110001101001000110 %
b10100011000001110001101001000110 )
#79000
b10110000011010100110100101100000 $
b10110000011010100110100101100000 ,
b110100100110000000011101101001 '
b110100100110000000011101101001 +
b1111011110100100110000111110111 %
b1111011110100100110000111110111 )
#80000
b11110011100000100100000111100 $
b11110011100000100100000111100 ,
b1000100000000011000110110001000 '
b1000100000000011000110110001000 +
b11011010011011101011101010110100 %
b11011010011011101011101010110100 )
#81000
b10101011000011001101110101010101 $
b10101011000011001101110101010101 ,
b10010110100100000000010000101101 '
b10010110100100000000010000101101 +
b10100011111001101100100101000 %
b10100011111001101100100101000 )
#82000
b1111011001000011100110011110101 $
b1111011001000011100110011110101 ,
b10010111010111001001110000101110 '
b10010111010111001001110000101110 +
b11100011110001010011000011000111 %
b11100011110001010011000011000111 )
#83000
b10010010101110010010100100100100 $
b10010010101110010010100100100100 ,
b1110010000010100010100011100 '
b1110010000010100010100011100 +
b10000100011101111110010000001000 %
b10000100011101111110010000001000 )
#84000
b10011010001011010111000100110 $
b10011010001011010111000100110 ,
b10100100111100000011100101001 '
b10100100111100000011100101001 +
b11111110101001111010011011111101 %
b11111110101001111010011011111101 )
#85000
b11010001011011001111011110100010 $
b11010001011011001111011110100010 ,
b1000011001101010110011110000110 '
b1000011001101010110011110000110 +
b10001110001101111001000000011100 %
b10001110001101111001000000011100 )
#86000
b10001011111010111100111100010111 $
b10001011111010111100111100010111 ,
b10011110101101111100011000111101 '
b10011110101101111100011000111101 +
b11101101001101000000100011011010 %
b11101101001101000000100011011010 )
#87000
b11101011101001000110101111010110 $
b11101011101001000110101111010110 ,
b10111000010101011100010001110000 '
b10111000010101011100010001110000 +
b110011010011101010011101100110 %
b110011010011101010011101100110 )
#88000
b10111011001101001111000101101 $
b10111011001101001111000101101 ,
b1011101011100011001100110111010 '
b1011101011100011001100110111010 +
b10111001111101010000010001110011 %
b10111001111101010000010001110011 )
#89000
b10101100100000100010110101011000 $
b10101100100000100010110101011000 ,
b1111101010001110111100111111010 '
b1111101010001110111100111111010 +
b101111001110101011001101011110 %
b101111001110101011001101011110 )
#90000
b11110111101100101111101111101111 $
b11110111101100101111101111101111 ,
b10001101001001001111011000011010 '
b10001101001001001111011000011010 +
b1101010100011100000010111010101 %
b1101010100011100000010111010101 )
#91000
b11111000011101110110000111110000 $
b11111000011101110110000111110000 ,
b11011100001110110000100110111 '
b11011100001110110000100110111 +
b11011100111100000000000010111001 %
b11011100111100000000000010111001 )
#92000
b10101011011000000101100101010110 $
b10101011011000000101100101010110 ,
b1100000001110010010000111000000 '
b1100000001110010010000111000000 +
b1001011001001110011011110010110 %
b1001011001001110011011110010110 )
#93000
b11101110011010111011100111011100 $
b11101110011010111011100111011100 ,
b11011011010001100001101010110110 '
b11011011010001100001101010110110 +
b10011001001011001111100100110 %
b10011001001011001111100100110 )
#94000
b10101100111110001001001101011001 $
b10101100111110001001001101011001 ,
b1101110010111110000111111011100 '
b1101110010111110000111111011100 +
b111110100110011000001101111101 %
b111110100110011000001101111101 )
#95000
b1111111011001010101011011111110 $
b1111111011001010101011011111110 ,
b111100000000111111111101111000 '
b111100000000111111111101111000 +
b1000011011000010101011110000110 %
b1000011011000010101011110000110 )
#96000
b101100111010000001110001011001 $
b101100111010000001110001011001 ,
b11101101100011011000000011011011 '
b11101101100011011000000011011011 +
b111111010110101001101101111110 %
b111111010110101001101101111110 )
#97000
b100100101100001110001001001000 $
b100100101100001110001001001000 ,
b111100111011010010101101111001 '
b111100111011010010101101111001 +
b11100111110000111011011011001111 %
b11100111110000111011011011001111 )
#98000
b10101101111001011101001101011011 $
b10101101111001011101001101011011 ,
b10110000101111001110111001100001 '
b10110000101111001110111001100001 +
b11111101001010001110010011111010 %
b11111101001010001110010011111010 )
#99000
b11011100100010011000000110111000 $
b11011100100010011000000110111000 ,
b11010000111101010111100010100001 '
b11010000111101010111100010100001 +
b1011100101000000100100010111 %
b1011100101000000100100010111 )
#100000
b11101011110110110010011111010110 $
b11101011110110110010011111010110 ,
b10101000011000111001011001010000 '
b10101000011000111001011001010000 +
b1000011011101111001000110000110 %
b1000011011101111001000110000110 )
#101000
b10101010000001110001000101010 $
b10101010000001110001000101010 ,
b10011010101101001000100000110101 '
b10011010101101001000100000110101 +
b1111010100011000101100111110101 %
b1111010100011000101100111110101 )
#102000
b11110101010010111111111111101010 $
b11110101010010111111111111101010 ,
b1100000101100010111010111000001 '
b1100000101100010111010111000001 +
b10010100100110101000101000101001 %
b10010100100110101000101000101001 )
#103000
b10101110111001110010100101011101 $
b10101110111001110010100101011101 ,
b11001100000000011011010010011000 '
b11001100000000011011010010011000 +
b11100010111001010111010011000101 %
b11100010111001010111010011000101 )
#104000
b11011111001111101011110110111110 $
b11011111001111101011110110111110 ,
b10111001100011000100001001110011 '
b10111001100011000100001001110011 +
b100101101100100111101101001011 %
b100101101100100111101101001011 )
#105000
b10111011011100101111110101110110 $
b10111011011100101111110101110110 ,
b11000101010100000001011010001010 '
b11000101010100000001011010001010 +
b11110110001000101110011011101100 %
b11110110001000101110011011101100 )
#106000
b11111011101001000101000111110110 $
b11111011101001000101000111110110 ,
b11010100010010111000000010101000 '
b11010100010010111000000010101000 +
b100111010110001101000101001110 %
b100111010110001101000101001110 )
#107000
b100101011010011000101001001010 $
b100101011010011000101001001010 ,
b11010000110010101000110010100001 '
b11010000110010101000110010100001 +
b1010100100111101111110110101001 %
b1010100100111101111110110101001 )
#108000
b11111010010000000001111111110100 $
b11111010010000000001111111110100 ,
b11110011001101000110011011100110 '
b11110011001101000110011011100110 +
b111000010111011100100001110 %
b111000010111011100100001110 )
#109000
b11100101000001100111010111001001 $
b11100101000001100111010111001001 ,
b10101001011111011010100101010 '
b10101001011111011010100101010 +
b11001111110101101100000010011111 %
b11001111110101101100000010011111 )
#110000
b11011100000100000001000110110111 $
b11011100000100000001000110110111 ,
b11000110101101011111010010001101 '
b11000110101101011111010010001101 +
b10101010110100001110100101010 %
b10101010110100001110100101010 )
#111000
b11101011111000111110010111010110 $
b11101011111000111110010111010110 ,
b10011100011011011110011000111000 '
b10011100011011011110011000111000 +
b1001111011101011111111110011110 %
b1001111011101011111111110011110 )
#112000
b100001001101001000110001000001 $
b100001001101001000110001000001 ,
b1100100011001001110001111001000 '
b1100100011001001110001111001000 +
b10111100110011111010100001111001 %
b10111100110011111010100001111001 )
#113000
b1101111001000101000011011011101 $
b1101111001000101000011011011101 ,
b1001111111110100000100010011 '
b1001111111110100000100010011 +
b1100101001000110100010111001010 %
b1100101001000110100010111001010 )
#114000
b11001010110000111100000110010 $
b11001010110000111100000110010 ,
b11100011101101111010111011000111 '
b11100011101101111010111011000111 +
b110101101000001100100101101011 %
b110101101000001100100101101011 )
#115000
b10111000000100010111101101110000 $
b10111000000100010111101101110000 ,
b1011101000001011001110110111010 '
b1011101000001011001110110111010 +
b1011011000010111101110110110110 %
b1011011000010111101110110110110 )
#116000
b10111110100110010100000101111101 $
b10111110100110010100000101111101 ,
b1011100100000101001010110111001 '
b1011100100000101001010110111001 +
b1100010000101101010101111000100 %
b1100010000101101010101111000100 )
#117000
b100011010101100110111001000110 $
b100011010101100110111001000110 ,
b11011010001001101001101010110100 '
b11011010001001101001101010110100 +
b1001001001011111101001110010010 %
b1001001001011111101001110010010 )
#118000
b10111011101100110000000101 $
b10111011101100110000000101 ,
b11000011001100111001000010000110 '
b11000011001100111001000010000110 +
b111111101110110011101101111111 %
b111111101110110011101101111111 )
#119000
b1110110100101011000101011101100 $
b1110110100101011000101011101100 ,
b11111001001001111001010011110010 '
b11111001001001111001010011110010 +
b1111101011011011111010111111010 %
b1111101011011011111010111111010 )
#120000
b11111000000100110111111111101111 $
b11111000000100110111111111101111 ,
b11011110110011100101111010111101 '
b11011110110011100101111010111101 +
b11001010001010010000100110010 %
b11001010001010010000100110010 )
#121000
b110100100110010111001001101000 $
b110100100110010111001001101000 ,
b11110010010010011010010011100100 '
b11110010010010011010010011100100 +
b1000010010011111100110110000100 %
b1000010010011111100110110000100 )
#122000
b10111001111011000100100101110011 $
b10111001111011000100100101110011 ,
b1010100101010000111100110101001 '
b1010100101010000111100110101001 +
b1100101010000111100111111001010 %
b1100101010000111100111111001010 )
#123000
b10111111110110101001000101111 $
b10111111110110101001000101111 ,
b1000111011001011010100110001110 '
b1000111011001011010100110001110 +
b11010000100101011010100010100001 %
b11010000100101011010100010100001 )
#124000
b10000011011100001000100100000110 $
b10000011011100001000100100000110 ,
b10000101111001010001111000001011 '
b10000101111001010001111000001011 +
b11111101100010110110101011111011 %
b11111101100010110110101011111011 )
#125000
b1011100010010101100111010111000 $
b1011100010010101100111010111000 ,
b1100100110010000011110111001001 '
b1100100110010000011110111001001 +
b11110111100000101001000011101111 %
b11110111100000101001000011101111 )
#126000
b11010110000100100010110110101011 $
b11010110000100100010110110101011 ,
b10111010101100010100100001110101 '
b10111010101100010100100001110101 +
b11011011000001110010100110110 %
b11011011000001110010100110110 )
#127000
b11111101101101100001010111111010 $
b11111101101101100001010111111010 ,
b110101110011011011111101101011 '
b110101110011011011111101101011 +
b11000111111010000101011010001111 %
b11000111111010000101011010001111 )
#128000
b11011101001011001110000110110 $
b11011101001011001110000110110 ,
b11010111001111111011010010101110 '
b11010111001111111011010010101110 +
b1000100011001011110011110001000 %
b1000100011001011110011110001000 )
#129000
b10010111001100011100011100101101 $
b10010111001100011100011100101101 ,
b1001001001111100100010110010010 '
b1001001001111100100010110010010 +
b1001101111100111000000110011011 %
b1001101111100111000000110011011 )
#130000
b10101010110010011011111101010101 $
b10101010110010011011111101010101 ,
b10010110100001001110000000101101 '
b10010110100001001110000000101101 +
b10100010001001101111100101000 %
b10100010001001101111100101000 )
#131000
b111001000010001000000001101 $
b111001000010001000000001101 ,
b11100001011010011011000011000010 '
b11100001011010011011000011000010 +
b100101101101110101111101001011 %
b100101101101110101111101001011 )
#132000
b10010101110011111111101100101011 $
b10010101110011111111101100101011 ,
b110101100110000010100001101 '
b110101100110000010100001101 +
b10001111000111001111011000011110 %
b10001111000111001111011000011110 )
#133000
b10000010011111011001101100000100 $
b10000010011111011001101100000100 ,
b1100000000111001110100011000 '
b1100000000111001110100011000 +
b1110110011110011111110111101100 %
b1110110011110011111110111101100 )
#134000
b101100001001000011100001010111 $
b101100001001000011100001010111 ,
b11000011011101100001110010000110 '
b11000011011101100001110010000110 +
b1101000101011100001101111010001 %
b1101000101011100001101111010001 )
#135000
b111110011111111000100001111100 $
b111110011111111000100001111100 ,
b10011101101111110110010000111011 '
b10011101101111110110010000111011 +
b10100000110000000010010001000001 %
b10100000110000000010010001000001 )
#136000
b10010110001101001110001100101011 $
b10010110001101001110001100101011 ,
b101001111011111110100101010011 '
b101001111011111110100101010011 +
b1101100010001001111100111011000 %
b1101100010001001111100111011000 )
#137000
b1011000110001011000010010110001 $
b1011000110001011000010010110001 ,
b10101101101011000010001001011011 '
b10101101101011000010001001011011 +
b10101011000110010110001001010110 %
b10101011000110010110001001010110 )
#138000
b1110011110110101101110011100110 $
b1110011110110101101110011100110 ,
b10000010011100111110001000000100 '
b10000010011100111110001000000100 +
b11110001011001101111101011100010 %
b11110001011001101111101011100010 )
#139000
b100101111111001011100001001011 $
b100101111111001011100001001011 ,
b11101100010100001011010011011000 '
b11101100010100001011010011011000 +
b111001101011000000001101110011 %
b111001101011000000001101110011 )
#140000
b11100101010000011001000111001010 $
b11100101010000011001000111001010 ,
b11011100000000110100010010111000 '
b11011100000000110100010010111000 +
b1001001111100100110100010010 %
b1001001111100100110100010010 )
#141000
b10001111000010001100100100011110 $
b10001111000010001100100100011110 ,
b11110010100001111011011011100101 '
b11110010100001111011011011100101 +
b10011100100000010001001000111001 %
b10011100100000010001001000111001 )
#142000
b11100110010011101110101111001100 $
b11100110010011101110101111001100 ,
b10101100010010000111100101011 '
b10101100010010000111100101011 +
b11010000110001011101110010100001 %
b11010000110001011101110010100001 )
#143000
b10100100101010111110001101001001 $
b10100100101010111110001101001001 ,
b1100100000110111000010111001000 '
b1100100000110111000010111001000 +
b1000000100100000101110110000001 %
b1000000100100000101110110000001 )
#144000
b1100100100010110100111011001000 $
b1100100100010110100111011001000 ,
b1010000110101011111100110100001 '
b1010000110101011111100110100001 +
b10011101101010101010100100111 %
b10011101101010101010100100111 )
#145000
b10001101011101010100000100011 $
b10001101011101010100000100011 ,
b10000010001000100011101000000100 '
b10000010001000100011101000000100 +
b10001111100011000110111000011111 %
b10001111100011000110111000011111 )
#146000
b11110111100010011010001111101110 $
b11110111100010011010001111101110 ,
b11001011010111001000000010010110 '
b11001011010111001000000010010110 +
b101100001011010010001101011000 %
b101100001011010010001101011000 )
